src/v/mxint8_includes.v

`ifndef MXINT8_INCLUDES

`define MXINT8_INCLUDES

`include "mx_general_includes.v"

`define MXINT8_ELEMENT_SIGN_BIT 7
`define MXINT8_ELEMENT_VALUE_BITS 6:0

`define MXINT8_ELEMENT_WIDTH 8

`endif // MXINT8_INCLUDES

src/v/scalar_includes.v

`ifndef SCALAR_INCLUDES

`define SCALAR_INCLUDES

`define FLOAT32_WIDTH 32

`define FLOAT32_SIGN_BIT 31

`define FLOAT32_MANTISSA_MSB 22
`define FLOAT32_MANTISSA_LSB 0
`define FLOAT32_MANTISSA_BITS `FLOAT32_MANTISSA_MSB:`FLOAT32_MANTISSA_LSB
`define FLOAT32_MANTISSA_WIDTH 23

`define FLOAT32_EXPONENT_MSB 30
`define FLOAT32_EXPONENT_LSB 23
`define FLOAT32_EXPONENT_BITS `FLOAT32_EXPONENT_MSB:`FLOAT32_EXPONENT_LSB
`define FLOAT32_EXPONENT_WIDTH 8

`define FLOAT32_MANTISSA_MXINT8_MSB `FLOAT32_MANTISSA_MSB
`define FLOAT32_MANTISSA_MXINT8_LSB 17
`define FLOAT32_MANTISSA_MXINT8_BITS `FLOAT32_MANTISSA_MXINT8_MSB:`FLOAT32_MANTISSA_MXINT8_LSB

`endif // SCALAR_INCLUDES

tb/tb_mxint8_bd_v/mx_int8_bd_mon.sv
`timescale 1ns/1ps
module mx_int8_bd_mon(
    i_float32,
    ref_o_scale,
    ref_o_mxint8_elements,
    ref_o_overflow,
    data_ready_i,
    clk
);
    `include "scalar_includes.v"
    `include "mxint8_includes.v"
    input wire data_ready_i;  
    input wire clk;

    input [`FLOAT32_WIDTH-1:0]              i_float32;  //same as float in c 
    input reg  [`SCALE_WIDTH-1:0]           ref_o_scale;
    input reg  [`MXINT8_ELEMENT_WIDTH-1:0]  ref_o_mxint8_elements [`BLOCK_SIZE-1:0];
    input reg                               ref_o_overflow;

    reg  [`MXINT8_ELEMENT_WIDTH-1:0] data_out;
    reg shortreal decoded_out;
    int transection_id; 

    initial begin
        transection_id = 0; 
    end

    always @(negedge clk) begin
        $display("\ntransection id: %d",transection_id);
        single_mon();
        transection_id <= transection_id + 1; 
    end

    task single_mon;
        reg same;
            same = 1'b1;
            data_out = ref_o_mxint8_elements[0];
            decoded_out = decoder(ref_o_mxint8_elements[0]);
            #0; 
            
            //$display("input data: %f, output data:", i_float32);                
            $display("input binary: \n%b",i_float32);
            $display("%b  :INT8 element mantissa output binary REF",{7'bXXX_XXXX,data_out});
            $display("%b  :E8M0 shared scalar output binary REF",{1'bX,ref_o_scale});
            $display("%b  :o_overflow output binary REF",ref_o_overflow);
            for(int i = 0; i < `BLOCK_SIZE-1; i = i + 1) begin
                if(ref_o_mxint8_elements[i] != ref_o_mxint8_elements[i+1]) begin
                    same = 1'b0;
                    $display("ERROR in broadcase e:%d != e:%d",i,i+1);
                end 
            end
            if(!same) begin
                $display("broadcase elements same ERROR");
                same = 1'b1; 
            end 
    endtask

    function automatic decoder(input reg[`MXINT8_ELEMENT_WIDTH-1:0] int8_data);
        shortreal scale;
        shortreal decimal_data;
        scale = 1.0;
        decimal_data = 0;
        for(int i = `MXINT8_ELEMENT_WIDTH-2 ; i >= 0 ; i = i - 1) begin
            if(int8_data[i]==1'b1)
                decimal_data += scale;
            scale = scale/2;
        end
        if(int8_data[`MXINT8_ELEMENT_WIDTH-1])
            decimal_data -= 2; 
        return decimal_data;
    endfunction
endmodule

tb/transection.sv
//`ifndef TRANSECTION__SV
//`define TRANSECTION__SV
`include "scalar_includes.v"
`include "mxint8_includes.v"

`define FLOAT32_MANTISSA_MXINT8_WIDTH `MXINT8_ELEMENT_WIDTH-2
`define FLOAT32_MANTISSA_MXINT8_WIDTH_CUT `FLOAT32_MANTISSA_WIDTH-(`FLOAT32_MANTISSA_MXINT8_WIDTH)
typedef reg[`MXINT8_ELEMENT_WIDTH-1:0] t_mx_int8;
typedef reg[`SCALE_WIDTH-1:0] t_scalar;

module t_mx_int8_vector(
    output t_scalar scalar,
    output t_mx_int8 elements[0:`BLOCK_SIZE-1]);

    reg is_nan;
    reg [$clog2(`BLOCK_SIZE):0] zero_num;

    task post_randomize();
        zero_num = 0; 
        foreach (elements[i]) begin
          if (elements[i] == 0) begin
            zero_num++;
          end
        end
    endtask

    task randomize();
        scalar = $random() % 256;
        foreach(elements[i])
            elements[i] = $random() % 256;
        post_randomize();
    endtask

    function void set_zero(int elem_index);
        if(elements[elem_index] != 0) begin
            elements[elem_index] = 0;
            zero_num++;
        end
    endfunction

endmodule

module op_negate_int8;
    output wire [7:0] input_scalar;
    output wire [7:0] output_scalar;
    output wire [7:0] input_elements[0:31];
    output wire [7:0] output_elements[0:31];

    t_mx_int8_vector a(.scalar(input_scalar),.elements(input_elements));
    t_mx_int8_vector result(.scalar(output_scalar),.elements(output_elements));

endmodule

module t_fp32_scalar(output [`FLOAT32_WIDTH-1:0] f);
    reg sign;
    reg sub_normal;
    reg NaN; 
    reg [`FLOAT32_EXPONENT_WIDTH-1:0] scalar;
    reg carry; 
    reg[1:0] tie2even; //lsb: whether valid, MSB whether carry  
    reg overflow; //mantissa overflow, scalar carry
    reg scalar_overflow;
    reg [`FLOAT32_MANTISSA_MXINT8_WIDTH-1:0] mantissa_high; 
    reg [`FLOAT32_MANTISSA_MXINT8_WIDTH_CUT-2:0] mantissa_low;
    reg mantissa_low_msb;  
    assign f = {sign,scalar,mantissa_high,mantissa_low_msb,mantissa_low};
    initial begin
        set_clean();
        randomize();
    end
    function void set_zero();
        {mantissa_high,mantissa_low_msb,mantissa_low} = `FLOAT32_MANTISSA_WIDTH'd0;
    endfunction
    function void set_clean();
        sign = 1'b0;
        sub_normal = 1'b0;
        NaN = 1'b0;
        carry = 1'b0;
        tie2even = 2'b00;
        overflow = 1'b0;
        scalar_overflow = 1'b0; 
    endfunction
    function [`FLOAT32_MANTISSA_MXINT8_WIDTH-1:0] random_high();
        return $urandom()%(1<<`FLOAT32_MANTISSA_MXINT8_WIDTH);
    endfunction
    function [`FLOAT32_MANTISSA_MXINT8_WIDTH_CUT-2:0] random_low();
        return $urandom()%(1<<(`FLOAT32_MANTISSA_MXINT8_WIDTH_CUT-1));
    endfunction
    function random_bit();
        return $urandom() % 2; 
    endfunction
    function void set_sign(input sign_i);
        sign = sign_i;
    endfunction
    function void set_carry(input c_i);//round causes carry, should't set tie2even = 01
        carry = c_i;
    endfunction
    function void set_overflow(input o_i);//carry causes mantissa overflow 
        overflow = o_i;
        carry = 1'b1; 
    endfunction
    function void set_NaN(input NaN_i);
        NaN = NaN_i; 
    endfunction
    function void set_tie2even();//0.5 whether carry or not// valid when carry == 1
        tie2even = {random_bit(),1'b1};
        carry = 1'b1;   
    endfunction
    function void set_scalar_overflow(input overflow_i);
        scalar_overflow = overflow_i;
        if(scalar_overflow) begin
            carry = 1'b1;
            overflow = 1'b1;
            NaN = 1'b0; 
        end
    endfunction
    function void randomize();
        if(sub_normal)
            scalar = `FLOAT32_EXPONENT_WIDTH'b0;
        else if(NaN)
            scalar = {`FLOAT32_EXPONENT_WIDTH{1'b1}};
        else
            scalar = $urandom() % (2<<`FLOAT32_EXPONENT_WIDTH-2) +1'b1;
        if(scalar_overflow)
            scalar = {`FLOAT32_EXPONENT_WIDTH{1'b1}}-1'b1;
        mantissa_high = random_high();
        mantissa_low = random_low();
        mantissa_low_msb = random_bit();
        if(carry) begin
            mantissa_low_msb = 1'b1;
            while(&mantissa_low)
                mantissa_low = random_low();
            if(tie2even[0]) begin
                mantissa_low_msb = 1'b1;
                mantissa_low = 0;
                mantissa_high[0] = tie2even[1]; 
            end
        end
        if(overflow)
            mantissa_high = (1<<`FLOAT32_MANTISSA_MXINT8_WIDTH) - 1; 
    endfunction
endmodule
//`endif

tb/tb_mxint8_bd_v/mx_int8_bd_drv.sv
`timescale 1ns/1ps
module mx_int8_bd_drv(
    gen_float32,
    data_ready_o,
    clk
);
    `include "scalar_includes.v"
    `include "mxint8_includes.v"
    input wire clk;
    output [`FLOAT32_WIDTH-1:0] gen_float32;  //same as float in c 
    output data_ready_o; 

    t_fp32_scalar data_in(.f(gen_float32));
    reg rand_ready;
    reg carry_ready;
    reg tie_ready;
    reg overflow_ready;
    reg sub_normal_ready;
    reg scalar_overflow_ready;
    reg NaN_ready; 
    assign data_ready_o = rand_ready || tie_ready || carry_ready|| overflow_ready|| sub_normal_ready|| scalar_overflow_ready|| NaN_ready ; 
    task single_drive();
        data_in.randomize(); 
        @(posedge clk) begin
            data_in.randomize();
            #1;
            rand_ready = 1'b1;
        end
        @(posedge clk) rand_ready = 1'b0;
    endtask

    task n_drive(int n);   
        data_in.set_sign(1'b0);
        repeat(n)
            single_drive();
        data_in.set_sign(1'b1);
        repeat(n)
            single_drive();
    endtask

    task carry_drive();     
        data_in.set_sign(1'b0);
        data_in.set_carry(1'b1);
        repeat(2) begin
            @(posedge clk) begin 
                data_in.randomize();
                #1;
                carry_ready = 1'b1; 
            end
            @(posedge clk) carry_ready = 1'b0;
            data_in.set_sign(1'b1); 
        end
        data_in.set_clean();
    endtask
    task tie_drive();     
        data_in.set_sign(1'b0);
        repeat(4) begin
            @(posedge clk) begin 
                data_in.set_tie2even();
                data_in.randomize();
                #1;
                tie_ready = 1'b1; 
            end
            @(posedge clk) tie_ready = 1'b0;
            data_in.set_sign(1'b1); 
        end
        data_in.set_clean();
    endtask
    task overflow_drive();     
        data_in.set_sign(1'b0);
        data_in.set_overflow(1'b1);
        repeat(2) begin
            @(posedge clk) begin                
                data_in.randomize();
                #1;
                overflow_ready = 1'b1; 
            end
            @(posedge clk) overflow_ready = 1'b0;
            data_in.set_sign(1'b1); 
        end
        data_in.set_clean();
    endtask
    task scalar_overflow_drive();     
        data_in.set_sign(1'b0);
        data_in.set_scalar_overflow(1'b1);
        repeat(2) begin
            @(posedge clk) begin                
                data_in.randomize();
                #1;
                scalar_overflow_ready = 1'b1; 
            end
            @(posedge clk) scalar_overflow_ready = 1'b0;
            data_in.set_sign(1'b1); 
        end
        data_in.set_clean();
    endtask
    task NaN_drive();  
        data_in.set_NaN(1'b1);  
        data_in.set_sign(1'b0);
        repeat(2) begin
            @(posedge clk) begin 
                data_in.randomize();
                #1;
                NaN_ready = 1'b1;                 
            end
            @(posedge clk) NaN_ready = 1'b0;
            data_in.set_sign(1'b1); 
        end
        $display("NaN carry");
        carry_drive();
        data_in.set_NaN(1'b1);
        $display("NaN overflow"); 
        overflow_drive();
        data_in.set_clean();
    endtask
    task sub_normal_drive();  
        data_in.set_clean();  
        data_in.sub_normal = 1'b1; 
        data_in.set_sign(1'b0);
        repeat(2) begin
            @(posedge clk) begin       
                data_in.randomize();
                #1;
                sub_normal_ready = 1'b1; 
                @(posedge clk) sub_normal_ready  = 1'b0;
            end
            data_in.set_sign(1'b1); 
        end
        data_in.set_carry(1'b1); 
        data_in.set_sign(1'b0);
        repeat(2) begin
            @(posedge clk) begin 
                data_in.sub_normal = 1'b1;
                data_in.randomize();
                #1;
                sub_normal_ready = 1'b1; 
                @(posedge clk) sub_normal_ready = 1'b0;
            end
            data_in.set_sign(1'b1); 
        end
        data_in.set_clean();
    endtask
    initial begin
        rand_ready = 1'b0;
        tie_ready = 1'b0;
        carry_ready = 1'b0;
        overflow_ready = 1'b0;
        sub_normal_ready = 1'b0;
        scalar_overflow_ready = 1'b0; 
        NaN_ready = 1'b0; 
        $display("normal case");
        n_drive(10);
        $display("carry case");
        repeat(3) 
            carry_drive();
        $display("tie to even case");
        repeat(3) 
            tie_drive();
        $display("mantissa overflow case");
        repeat(3) 
            overflow_drive();
        $display("scalar overflow case. due to round and mantissa overflow caused scalar carry. scalar carrys to NaN");
        repeat(3) 
            scalar_overflow_drive();
        $display("scalar NaN case");
        repeat(3) 
            NaN_drive();
        $display("subnormal case");
        repeat(3) 
            sub_normal_drive();
        $finish();
    end
endmodule

tb/tb_mxint8_bd_v/mx_int8_bd_ref.sv
module mx_int8_bd_ref (
    i_float32,
    o_scale,
    o_mxint8_elements,
    o_overflow
);

    `include "scalar_includes.v"
    `include "mxint8_includes.v"

    input  wire [`FLOAT32_WIDTH-1:0]         i_float32;
    output reg  [`SCALE_WIDTH-1:0]           o_scale;
    output reg  [`MXINT8_ELEMENT_WIDTH-1:0]  o_mxint8_elements [`BLOCK_SIZE-1:0];
    output reg                               o_overflow;

    wire [`FLOAT32_MANTISSA_WIDTH-1:0]   fp32_mantissa;
    wire [1+`FLOAT32_MANTISSA_WIDTH-1:0] fp32_m;
    wire fp32_sign;
    wire [`FLOAT32_EXPONENT_WIDTH-1:0]   fp32_scalar;

    assign fp32_sign = i_float32[`FLOAT32_SIGN_BIT];
    assign fp32_scalar = i_float32[`FLOAT32_EXPONENT_BITS];
    assign fp32_mantissa = i_float32[`FLOAT32_MANTISSA_BITS];
    assign fp32_m = (fp32_scalar == `FLOAT32_EXPONENT_WIDTH'd0) ? 
                    {1'b0,fp32_mantissa} : {1'b1,fp32_mantissa};


    wire [`MXINT8_ELEMENT_WIDTH-1:0]     fp_m_high;//{0,LSB 7 bit fp32_m}
    wire [1+`FLOAT32_MANTISSA_WIDTH-`MXINT8_ELEMENT_WIDTH+1-1:0] fp_m_low; 
    reg [`MXINT8_ELEMENT_WIDTH-1:0]     fp_round; 
    reg carry; 
    wire larger; 
    assign larger = ^fp_m_low[`FLOAT32_MANTISSA_WIDTH-`MXINT8_ELEMENT_WIDTH:0];
    
    assign fp_m_high ={1'b0, fp32_m[`FLOAT32_MANTISSA_WIDTH:`FLOAT32_MANTISSA_WIDTH-(`MXINT8_ELEMENT_WIDTH-1)+1]};
    assign fp_m_low = fp32_m[`FLOAT32_MANTISSA_WIDTH-(`MXINT8_ELEMENT_WIDTH-1):0];
    always@(*) begin
        carry = carry_logic(fp_m_high[0],larger,fp_m_low[`FLOAT32_MANTISSA_WIDTH-(`MXINT8_ELEMENT_WIDTH-1)]);
    end
    always@(*) begin
        fp_round = carry + fp_m_high;
    end

    wire overflow;
    assign overflow = fp_round[`MXINT8_ELEMENT_WIDTH-1];
    assign o_overflow = overflow&&(&fp32_scalar[`FLOAT32_EXPONENT_WIDTH-1:1])&&(!fp32_scalar[0])? 1'b1: 1'b0; 
    assign o_scale =  (&fp32_scalar)? fp32_scalar :(overflow? fp32_scalar+1'b1 : fp32_scalar);

    wire [`MXINT8_ELEMENT_WIDTH-1:0]     fp_round_unsigned;
    assign fp_round_unsigned = overflow? {1'b0,fp_round[`MXINT8_ELEMENT_WIDTH-1:1]}:{1'b0,fp_round[`MXINT8_ELEMENT_WIDTH-2:0]};

    reg [`MXINT8_ELEMENT_WIDTH-1:0]fp_round_signed;
    always@(*) begin
        fp_round_signed = sign_conv(fp32_sign,fp_round_unsigned);
    end
    genvar i;
    generate
        for(i=0;i<`BLOCK_SIZE;i=i+1)
            assign o_mxint8_elements[i] = fp_round_signed;
    endgenerate


    function [`MXINT8_ELEMENT_WIDTH-1:0] sign_conv(input sign_bit, input[`MXINT8_ELEMENT_WIDTH-1:0] unsigned_int);
        if(!sign_bit)
            return unsigned_int;
        else
            return (~unsigned_int) + 1'b1; 
    endfunction

    function carry_logic(input high_lsb,
                     input larger,
                     input low_msb);
        if(!low_msb) 
            return 1'b0;
        else if(larger)
            return 1'b1;
        else 
            return high_lsb;
    endfunction 
endmodule

tb/tb_mxint8_bd_v/tb_mxint8_bd.sv
`timescale 1ns/1ps
`define CYCLE 100
module tb_mxint8_bd; 
    
    bit clk;
    wire data_ready;
    wire [`FLOAT32_WIDTH-1:0]         i_float32;
    wire [`SCALE_WIDTH-1:0]           o_scale_ref;
    wire [`MXINT8_ELEMENT_WIDTH-1:0]  o_mxint8_elements_ref [`BLOCK_SIZE-1:0];
    wire                              o_overflow_ref;
    mx_int8_bd_ref ref_blk (
        .i_float32(i_float32),
        .o_scale(o_scale_ref),
        .o_mxint8_elements(o_mxint8_elements_ref),
        .o_overflow(o_overflow_ref)
    );

    mx_int8_bd_drv drv(
        .gen_float32(i_float32),
        .data_ready_o(data_ready),
        .clk(clk)
    );

    mx_int8_bd_mon mon(
    .i_float32(i_float32),
    .ref_o_scale(o_scale_ref),
    .ref_o_mxint8_elements(o_mxint8_elements_ref),
    .ref_o_overflow(o_overflow_ref),
    .data_ready_i(data_ready),
    .clk(clk)
    );

    initial begin
        clk = 1'b0;
        forever begin
          #(`CYCLE/2)  clk = ~ clk;
        end
    end

    initial begin
        $dumpfile("test.vcd");
        $dumpvars(0,tb_mxint8_bd);
    end
endmodule

tb/tb_mxint8_bd_v/test.vcd
$date
	Wed Sep 04 15:23:09 2024
$end
$version
	Icarus Verilog
$end
$timescale
	1ps
$end
$scope module tb_mxint8_bd $end
$var wire 8 ! o_scale_ref [7:0] $end
$var wire 1 " o_overflow_ref $end
$var wire 32 # i_float32 [31:0] $end
$var wire 1 $ data_ready $end
$var reg 1 % clk $end
$scope module drv $end
$var wire 1 % clk $end
$var wire 1 $ data_ready_o $end
$var wire 32 & gen_float32 [31:0] $end
$var reg 1 ' NaN_ready $end
$var reg 1 ( carry_ready $end
$var reg 1 ) overflow_ready $end
$var reg 1 * rand_ready $end
$var reg 1 + scalar_overflow_ready $end
$var reg 1 , sub_normal_ready $end
$var reg 1 - tie_ready $end
$scope module data_in $end
$var wire 32 . f [31:0] $end
$var reg 1 / NaN $end
$var reg 1 0 carry $end
$var reg 6 1 mantissa_high [5:0] $end
$var reg 16 2 mantissa_low [15:0] $end
$var reg 1 3 mantissa_low_msb $end
$var reg 1 4 overflow $end
$var reg 8 5 scalar [7:0] $end
$var reg 1 6 scalar_overflow $end
$var reg 1 7 sign $end
$var reg 1 8 sub_normal $end
$var reg 2 9 tie2even [1:0] $end
$scope function random_bit $end
$upscope $end
$scope function random_high $end
$upscope $end
$scope function random_low $end
$upscope $end
$scope function randomize $end
$upscope $end
$scope function set_NaN $end
$var reg 1 : NaN_i $end
$upscope $end
$scope function set_carry $end
$var reg 1 ; c_i $end
$upscope $end
$scope function set_clean $end
$upscope $end
$scope function set_overflow $end
$var reg 1 < o_i $end
$upscope $end
$scope function set_scalar_overflow $end
$var reg 1 = overflow_i $end
$upscope $end
$scope function set_sign $end
$var reg 1 > sign_i $end
$upscope $end
$scope function set_tie2even $end
$upscope $end
$upscope $end
$scope task NaN_drive $end
$upscope $end
$scope task carry_drive $end
$upscope $end
$scope task n_drive $end
$var integer 32 ? n [31:0] $end
$upscope $end
$scope task overflow_drive $end
$upscope $end
$scope task scalar_overflow_drive $end
$upscope $end
$scope task single_drive $end
$upscope $end
$scope task sub_normal_drive $end
$upscope $end
$scope task tie_drive $end
$upscope $end
$upscope $end
$scope module mon $end
$var wire 1 % clk $end
$var wire 1 $ data_ready_i $end
$var wire 32 @ i_float32 [31:0] $end
$var wire 8 A ref_o_scale [7:0] $end
$var wire 1 " ref_o_overflow $end
$var reg 8 B data_out [7:0] $end
$var real 1 C decoded_out $end
$var integer 32 D transection_id [31:0] $end
$scope function decoder $end
$scope begin $ivl_for_loop1 $end
$upscope $end
$upscope $end
$scope task single_mon $end
$var reg 1 E same $end
$scope begin $ivl_for_loop0 $end
$var integer 32 F i [31:0] $end
$upscope $end
$upscope $end
$upscope $end
$scope module ref_blk $end
$var wire 32 G i_float32 [31:0] $end
$var wire 1 H overflow $end
$var wire 8 I o_scale [7:0] $end
$var wire 1 " o_overflow $end
$var wire 1 J larger $end
$var wire 8 K fp_round_unsigned [7:0] $end
$var wire 17 L fp_m_low [16:0] $end
$var wire 8 M fp_m_high [7:0] $end
$var wire 1 N fp32_sign $end
$var wire 8 O fp32_scalar [7:0] $end
$var wire 23 P fp32_mantissa [22:0] $end
$var wire 24 Q fp32_m [23:0] $end
$var reg 1 R carry $end
$var reg 8 S fp_round [7:0] $end
$var reg 8 T fp_round_signed [7:0] $end
$scope function carry_logic $end
$var reg 1 U high_lsb $end
$var reg 1 V larger $end
$var reg 1 W low_msb $end
$upscope $end
$scope function sign_conv $end
$var reg 1 X sign_bit $end
$var reg 8 Y unsigned_int [7:0] $end
$upscope $end
$scope begin genblk1[0] $end
$var parameter 2 Z i $end
$upscope $end
$scope begin genblk1[1] $end
$var parameter 2 [ i $end
$upscope $end
$scope begin genblk1[2] $end
$var parameter 3 \ i $end
$upscope $end
$scope begin genblk1[3] $end
$var parameter 3 ] i $end
$upscope $end
$scope begin genblk1[4] $end
$var parameter 4 ^ i $end
$upscope $end
$scope begin genblk1[5] $end
$var parameter 4 _ i $end
$upscope $end
$scope begin genblk1[6] $end
$var parameter 4 ` i $end
$upscope $end
$scope begin genblk1[7] $end
$var parameter 4 a i $end
$upscope $end
$scope begin genblk1[8] $end
$var parameter 5 b i $end
$upscope $end
$scope begin genblk1[9] $end
$var parameter 5 c i $end
$upscope $end
$scope begin genblk1[10] $end
$var parameter 5 d i $end
$upscope $end
$scope begin genblk1[11] $end
$var parameter 5 e i $end
$upscope $end
$scope begin genblk1[12] $end
$var parameter 5 f i $end
$upscope $end
$scope begin genblk1[13] $end
$var parameter 5 g i $end
$upscope $end
$scope begin genblk1[14] $end
$var parameter 5 h i $end
$upscope $end
$scope begin genblk1[15] $end
$var parameter 5 i i $end
$upscope $end
$scope begin genblk1[16] $end
$var parameter 6 j i $end
$upscope $end
$scope begin genblk1[17] $end
$var parameter 6 k i $end
$upscope $end
$scope begin genblk1[18] $end
$var parameter 6 l i $end
$upscope $end
$scope begin genblk1[19] $end
$var parameter 6 m i $end
$upscope $end
$scope begin genblk1[20] $end
$var parameter 6 n i $end
$upscope $end
$scope begin genblk1[21] $end
$var parameter 6 o i $end
$upscope $end
$scope begin genblk1[22] $end
$var parameter 6 p i $end
$upscope $end
$scope begin genblk1[23] $end
$var parameter 6 q i $end
$upscope $end
$scope begin genblk1[24] $end
$var parameter 6 r i $end
$upscope $end
$scope begin genblk1[25] $end
$var parameter 6 s i $end
$upscope $end
$scope begin genblk1[26] $end
$var parameter 6 t i $end
$upscope $end
$scope begin genblk1[27] $end
$var parameter 6 u i $end
$upscope $end
$scope begin genblk1[28] $end
$var parameter 6 v i $end
$upscope $end
$scope begin genblk1[29] $end
$var parameter 6 w i $end
$upscope $end
$scope begin genblk1[30] $end
$var parameter 6 x i $end
$upscope $end
$scope begin genblk1[31] $end
$var parameter 6 y i $end
$upscope $end
$upscope $end
$upscope $end
$enddefinitions $end
$comment Show the parameter values. $end
$dumpall
b11111 y
b11110 x
b11101 w
b11100 v
b11011 u
b11010 t
b11001 s
b11000 r
b10111 q
b10110 p
b10101 o
b10100 n
b10011 m
b10010 l
b10001 k
b10000 j
b1111 i
b1110 h
b1101 g
b1100 f
b1011 e
b1010 d
b1001 c
b1000 b
b111 a
b110 `
b101 _
b100 ^
b11 ]
b10 \
b1 [
b0 Z
$end
#0
$dumpvars
b1001101 Y
0X
0W
0V
1U
b1001101 T
b1001101 S
0R
b100110101000010001100101 Q
b110101000010001100101 P
b1110 O
0N
b1001101 M
b1000010001100101 L
b1001101 K
0J
b1110 I
0H
b111000110101000010001100101 G
b0 F
xE
b0 D
r0 C
bx B
b1110 A
b111000110101000010001100101 @
b1010 ?
0>
x=
x<
x;
x:
b0 9
08
07
06
b1110 5
04
03
b1000010001100101 2
b1101 1
00
0/
b111000110101000010001100101 .
0-
0,
0+
0*
0)
0(
0'
b111000110101000010001100101 &
0%
0$
b111000110101000010001100101 #
0"
b1110 !
$end
#50000
b1001110 T
b1001110 Y
b1001110 K
b1001110 S
1R
1W
b11111000101110110 L
b10 !
b10 A
b10 I
b100110111111000101110110 Q
b110111111000101110110 P
b10 O
13
b1111000101110110 2
b1000110111111000101110110 #
b1000110111111000101110110 &
b1000110111111000101110110 .
b1000110111111000101110110 @
b1000110111111000101110110 G
b10 5
1%
#51000
1$
1*
#100000
b1 D
b11111 F
r1 C
b1001110 B
1E
0%
#150000
b1001100 T
b1001100 Y
b1001100 K
0$
1V
b1001100 S
1J
0R
0U
0W
b1001100 M
b1110100111111001 L
b1101110 !
b1101110 A
b1101110 I
b100110001110100111111001 Q
b110001110100111111001 P
b1101110 O
03
b1110100111111001 2
b1100 1
b110111000110001110100111111001 #
b110111000110001110100111111001 &
b110111000110001110100111111001 .
b110111000110001110100111111001 @
b110111000110001110100111111001 G
b1101110 5
0*
1%
#200000
b10 D
b11111 F
b1001100 B
0%
#250000
b1101010 T
b1101010 Y
b1101010 K
0V
b1101010 S
0J
0R
1W
b1101010 M
b11111011111100101 L
b1000110 !
b1000110 A
b1000110 I
b110101011111011111100101 Q
b10101011111011111100101 P
b1000110 O
13
b1111011111100101 2
b101010 1
b100011010101011111011111100101 #
b100011010101011111011111100101 &
b100011010101011111011111100101 .
b100011010101011111011111100101 @
b100011010101011111011111100101 G
b1000110 5
1%
#251000
1$
1*
#300000
b11 D
b11111 F
r0 C
b1101010 B
0%
#350000
b1001111 T
b1001111 Y
b1001111 K
0$
1V
b1001111 S
1J
1U
0W
b1001111 M
b110100111110010 L
b10011 !
b10011 A
b10011 I
b100111100110100111110010 Q
b111100110100111110010 P
b10011 O
03
b110100111110010 2
b1111 1
b1001100111100110100111110010 #
b1001100111100110100111110010 &
b1001100111100110100111110010 .
b1001100111100110100111110010 @
b1001100111100110100111110010 G
b10011 5
0*
1%
#400000
b100 D
b11111 F
r1 C
b1001111 B
0%
#450000
b1000110 T
b1000110 Y
b1000110 K
b1000110 S
1R
1W
b1000101 M
b10100100101011100 L
b1101001 !
b1101001 A
b1101001 I
b100010110100100101011100 Q
b10110100100101011100 P
b1101001 O
13
b100100101011100 2
b101 1
b110100100010110100100101011100 #
b110100100010110100100101011100 &
b110100100010110100100101011100 .
b110100100010110100100101011100 @
b110100100010110100100101011100 G
b1101001 5
1%
#451000
1$
1*
#500000
b101 D
b11111 F
b1000110 B
0%
#550000
b1100101 T
b1100101 Y
b1100101 K
0$
b1100101 S
0R
0W
b1100101 M
b110001001100011 L
b101110 !
b101110 A
b101110 I
b110010100110001001100011 Q
b10010100110001001100011 P
b101110 O
03
b110001001100011 2
b100101 1
b10111010010100110001001100011 #
b10111010010100110001001100011 &
b10111010010100110001001100011 .
b10111010010100110001001100011 @
b10111010010100110001001100011 G
b101110 5
0*
1%
#600000
b110 D
b11111 F
r0 C
b1100101 B
0%
#650000
b1100001 T
b1100001 Y
b1100001 K
b1100001 S
1R
0U
1W
b1100000 M
b10100010110101010 L
b1 !
b1 A
b1 I
b110000010100010110101010 Q
b10000010100010110101010 P
b1 O
13
b100010110101010 2
b100000 1
b110000010100010110101010 #
b110000010100010110101010 &
b110000010100010110101010 .
b110000010100010110101010 @
b110000010100010110101010 G
b1 5
1%
#651000
1$
1*
#700000
b111 D
b11111 F
b1100001 B
0%
#750000
b1010100 T
b1010100 Y
b1010100 K
0$
0V
b1010100 S
0J
1U
b1010011 M
b10011100000001101 L
b10111 !
b10111 A
b10111 I
b101001110011100000001101 Q
b1001110011100000001101 P
b10111 O
b11100000001101 2
b10011 1
b1011101001110011100000001101 #
b1011101001110011100000001101 &
b1011101001110011100000001101 .
b1011101001110011100000001101 @
b1011101001110011100000001101 G
b10111 5
0*
1%
#800000
b1000 D
b11111 F
r1 C
b1010100 B
0%
#850000
b1010101 T
b1010101 Y
b1010101 K
b1010101 S
0R
0W
b1010101 M
b100101000000010 L
b1101100 !
b1101100 A
b1101100 I
b101010100100101000000010 Q
b1010100100101000000010 P
b1101100 O
03
b100101000000010 2
b10101 1
b110110001010100100101000000010 #
b110110001010100100101000000010 &
b110110001010100100101000000010 .
b110110001010100100101000000010 @
b110110001010100100101000000010 G
b1101100 5
1%
#851000
1$
1*
#900000
b1001 D
b11111 F
b1010101 B
0%
#950000
b1001111 T
b1001111 Y
b1001111 K
0$
b1001111 S
b1001111 M
b100100100100011 L
b11110 !
b11110 A
b11110 I
b100111100100100100100011 Q
b111100100100100100011 P
b11110 O
b100100100100011 2
b1111 1
b1111000111100100100100100011 #
b1111000111100100100100100011 &
b1111000111100100100100100011 .
b1111000111100100100100100011 @
b1111000111100100100100100011 G
b11110 5
0*
1%
#1000000
b1010 D
b11111 F
b1001111 B
0%
#1050000
b1111100 T
b1111100 Y
b1111100 K
1V
b1111100 S
1J
0U
b1111100 M
b1011110111110010 L
b1001011 !
b1001011 A
b1001011 I
b111110001011110111110010 Q
b11110001011110111110010 P
b1001011 O
b1011110111110010 2
b111100 1
b100101111110001011110111110010 #
b100101111110001011110111110010 &
b100101111110001011110111110010 .
b100101111110001011110111110010 @
b100101111110001011110111110010 G
b1001011 5
1%
#1051000
1$
1*
#1100000
b1011 D
b11111 F
r0 C
b1111100 B
0%
#1150000
b1011000 T
b1011000 Y
b1011000 K
0$
0V
b1011000 S
0J
0R
1W
b1011000 M
b11111001101111000 L
b1000010 !
b1000010 A
b1000010 I
b101100011111001101111000 Q
b1100011111001101111000 P
b1000010 O
13
b1111001101111000 2
b11000 1
b100001001100011111001101111000 #
b100001001100011111001101111000 &
b100001001100011111001101111000 .
b100001001100011111001101111000 @
b100001001100011111001101111000 G
b1000010 5
0*
1%
#1200000
b1100 D
b11111 F
r1 C
b1011000 B
0%
#1250000
b1110110 T
b1110110 Y
b1110110 K
b1110110 S
0W
b1110110 M
b1111100111000110 L
b1101100 !
b1101100 A
b1101100 I
b111011001111100111000110 Q
b11011001111100111000110 P
b1101100 O
03
b1111100111000110 2
b110110 1
b110110011011001111100111000110 #
b110110011011001111100111000110 &
b110110011011001111100111000110 .
b110110011011001111100111000110 @
b110110011011001111100111000110 G
b1101100 5
1%
#1251000
1$
1*
#1300000
b1101 D
b11111 F
r0 C
b1110110 B
0%
