src/v/mxint8_includes.v

`ifndef MXINT8_INCLUDES

`define MXINT8_INCLUDES

`include "mx_general_includes.v"

`define MXINT8_ELEMENT_SIGN_BIT 7
`define MXINT8_ELEMENT_VALUE_BITS 6:0

`define MXINT8_ELEMENT_WIDTH 8

`endif // MXINT8_INCLUDES

src/v/scalar_includes.v

`ifndef SCALAR_INCLUDES

`define SCALAR_INCLUDES

`define FLOAT32_WIDTH 32

`define FLOAT32_SIGN_BIT 31

`define FLOAT32_MANTISSA_MSB 22
`define FLOAT32_MANTISSA_LSB 0
`define FLOAT32_MANTISSA_BITS `FLOAT32_MANTISSA_MSB:`FLOAT32_MANTISSA_LSB
`define FLOAT32_MANTISSA_WIDTH 23

`define FLOAT32_EXPONENT_MSB 30
`define FLOAT32_EXPONENT_LSB 23
`define FLOAT32_EXPONENT_BITS `FLOAT32_EXPONENT_MSB:`FLOAT32_EXPONENT_LSB
`define FLOAT32_EXPONENT_WIDTH 8

`define FLOAT32_MANTISSA_MXINT8_MSB `FLOAT32_MANTISSA_MSB
`define FLOAT32_MANTISSA_MXINT8_LSB 17
`define FLOAT32_MANTISSA_MXINT8_BITS `FLOAT32_MANTISSA_MXINT8_MSB:`FLOAT32_MANTISSA_MXINT8_LSB

`endif // SCALAR_INCLUDES

tb/tb_mxint8_negate_v/mx_int8_negate_mon.sv
`timescale 1ns/1ps
module mx_int8_negate_mon(
    dut_in_mxint8_elements,
    dut_out_mxint8_elements,
    data_ready_i,
    clk
);
    `include "scalar_includes.v"
    `include "mxint8_includes.v"
    input wire data_ready_i;  
    input wire clk;
    input wire [`MXINT8_ELEMENT_WIDTH-1:0] dut_in_mxint8_elements[0:`BLOCK_SIZE-1];
    input wire [`MXINT8_ELEMENT_WIDTH-1:0] dut_out_mxint8_elements[0:`BLOCK_SIZE-1];
    reg real decoded_in;
    reg real decoded_out;
    int transection_id; 

    initial begin
        transection_id = 0; 
    end

    always @(posedge data_ready_i) begin
        $display("\ntransection id: %d",transection_id);
        single_mon();
        transection_id <= transection_id + 1; 
    end

    task single_mon;
        for(int i = 0; i < `BLOCK_SIZE; i = i + 1) begin
            @(posedge clk) begin
                decoder(dut_in_mxint8_elements[i],decoded_in);
                decoder(dut_out_mxint8_elements[i],decoded_out);
                #0; 
                $display("element index: %d",i);
                if(decoded_in != (-decoded_out))
                    $display("MXINT8_NEGATE ERROR!");
                $display("input data: %f, output data: %f", decoded_in,decoded_out);
                $display("input binary: \n%b",dut_in_mxint8_elements[i]);
                $display("%b\noutput binary",dut_out_mxint8_elements[i]);
                end
        end
    endtask

    task automatic decoder(input reg[`MXINT8_ELEMENT_WIDTH-1:0] int8_data, output real decimal_data);
        real scale;
        scale = 1.0;
        decimal_data = 0;
        for(int i = `MXINT8_ELEMENT_WIDTH-2 ; i >= 0 ; i = i - 1) begin
            if(int8_data[i]==1'b1)
                decimal_data += scale;
            scale = scale/2;
        end
        if(int8_data[`MXINT8_ELEMENT_WIDTH-1])
            decimal_data -= 2; 
    endtask
endmodule

tb/transection.sv
//`ifndef TRANSECTION__SV
//`define TRANSECTION__SV
`include "scalar_includes.v"
`include "mxint8_includes.v"

`define FLOAT32_MANTISSA_MXINT8_WIDTH `MXINT8_ELEMENT_WIDTH-2
`define FLOAT32_MANTISSA_MXINT8_WIDTH_CUT `FLOAT32_MANTISSA_WIDTH-(`FLOAT32_MANTISSA_MXINT8_WIDTH)
typedef reg[`MXINT8_ELEMENT_WIDTH-1:0] t_mx_int8;
typedef reg[`SCALE_WIDTH-1:0] t_scalar;

module t_mx_int8_vector(
    output t_scalar scalar,
    output t_mx_int8 elements[0:`BLOCK_SIZE-1]);

    reg is_nan;
    reg [$clog2(`BLOCK_SIZE):0] zero_num;

    task post_randomize();
        zero_num = 0; 
        foreach (elements[i]) begin
          if (elements[i] == 0) begin
            zero_num++;
          end
        end
    endtask

    task randomize();
        scalar = $random() % 256;
        foreach(elements[i])
            elements[i] = $random() % 256;
        post_randomize();
    endtask

    function void set_zero(int elem_index);
        if(elements[elem_index] != 0) begin
            elements[elem_index] = 0;
            zero_num++;
        end
    endfunction

endmodule

module op_negate_int8;
    output wire [7:0] input_scalar;
    output wire [7:0] output_scalar;
    output wire [7:0] input_elements[0:31];
    output wire [7:0] output_elements[0:31];

    t_mx_int8_vector a(.scalar(input_scalar),.elements(input_elements));
    t_mx_int8_vector result(.scalar(output_scalar),.elements(output_elements));

endmodule

module t_fp32_scalar(output [`FLOAT32_WIDTH-1:0] f);
    reg sign;
    reg sub_normal;
    reg NaN; 
    reg [`FLOAT32_EXPONENT_WIDTH-1:0] scalar;
    reg carry; 
    reg[1:0] tie2even; //lsb: whether valid, MSB whether carry  
    reg overflow; //mantissa overflow, scalar carry
    reg scalar_overflow;
    reg [`FLOAT32_MANTISSA_MXINT8_WIDTH-1:0] mantissa_high; 
    reg [`FLOAT32_MANTISSA_MXINT8_WIDTH_CUT-2:0] mantissa_low;
    reg mantissa_low_msb;  
    assign f = {sign,scalar,mantissa_high,mantissa_low_msb,mantissa_low};
    initial begin
        set_clean();
        randomize();
    end
    function void set_zero();
        {mantissa_high,mantissa_low_msb,mantissa_low} = `FLOAT32_MANTISSA_WIDTH'd0;
    endfunction
    function void set_clean();
        sign = 1'b0;
        sub_normal = 1'b0;
        NaN = 1'b0;
        carry = 1'b0;
        tie2even = 2'b00;
        overflow = 1'b0;
        scalar_overflow = 1'b0; 
    endfunction
    function [`FLOAT32_MANTISSA_MXINT8_WIDTH-1:0] random_high();
        return $urandom()%(1<<`FLOAT32_MANTISSA_MXINT8_WIDTH);
    endfunction
    function [`FLOAT32_MANTISSA_MXINT8_WIDTH_CUT-2:0] random_low();
        return $urandom()%(1<<(`FLOAT32_MANTISSA_MXINT8_WIDTH_CUT-1));
    endfunction
    function random_bit();
        return $urandom() % 2; 
    endfunction
    function void set_sign(input sign_i);
        sign = sign_i;
    endfunction
    function void set_carry(input c_i);//round causes carry, should't set tie2even = 01
        carry = c_i;
    endfunction
    function void set_overflow(input o_i);//carry causes mantissa overflow 
        overflow = o_i;
        carry = 1'b1; 
    endfunction
    function void set_NaN(input NaN_i);
        NaN = NaN_i; 
    endfunction
    function void set_tie2even();//0.5 whether carry or not// valid when carry == 1
        tie2even = {random_bit(),1'b1};
        carry = 1'b1;   
    endfunction
    function void set_scalar_overflow(input overflow_i);
        scalar_overflow = overflow_i;
        if(scalar_overflow) begin
            carry = 1'b1;
            overflow = 1'b1;
            NaN = 1'b0; 
        end
    endfunction
    function void randomize();
        if(sub_normal)
            scalar = `FLOAT32_EXPONENT_WIDTH'b0;
        else if(NaN)
            scalar = {`FLOAT32_EXPONENT_WIDTH{1'b1}};
        else
            scalar = $urandom() % (2<<`FLOAT32_EXPONENT_WIDTH-2) +1'b1;
        if(scalar_overflow)
            scalar = {`FLOAT32_EXPONENT_WIDTH{1'b1}}-1'b1;
        mantissa_high = random_high();
        mantissa_low = random_low();
        mantissa_low_msb = random_bit();
        if(carry) begin
            mantissa_low_msb = 1'b1;
            while(&mantissa_low)
                mantissa_low = random_low();
            if(tie2even[0]) begin
                mantissa_low_msb = 1'b1;
                mantissa_low = 0;
                mantissa_high[0] = tie2even[1]; 
            end
        end
        if(overflow)
            mantissa_high = (1<<`FLOAT32_MANTISSA_MXINT8_WIDTH) - 1; 
    endfunction
endmodule
//`endif

tb/tb_mxint8_negate_v/mx_int8_negate_drv.sv
`timescale 1ns/1ps
module mx_int8_negate_drv(
    gen_mxint8_elements,
    data_ready_o,
    clk
);
    `include "scalar_includes.v"
    `include "mxint8_includes.v"
    input wire clk;
    output wire [`MXINT8_ELEMENT_WIDTH-1:0] gen_mxint8_elements[0:`BLOCK_SIZE-1] ;
    output wire data_ready_o; 
    t_mx_int8_vector data_in(.elements(gen_mxint8_elements));
    reg rand_ready;
    reg zero_ready;
    assign data_ready_o = rand_ready || zero_ready; 
    task single_drive();
        data_in.randomize(); 
        @(posedge clk) begin
            data_in.randomize();
            #1;
            rand_ready = 1'b1;
            repeat(`BLOCK_SIZE) begin
                @(posedge clk) rand_ready = 1'b0;
            end
        end
    endtask

    task n_drive(int n);   
        repeat(n)
            single_drive();
    endtask

    task zero_drive();     
        logic [$clog2(`BLOCK_SIZE)-1:0] zero_index;  
        @(posedge clk) begin
            zero_index = $urandom() % `BLOCK_SIZE;
            data_in.randomize();
            data_in.set_zero(zero_index);
            #1;
            $display("zero element index: %d", zero_index);
            zero_ready = 1'b1; 
            repeat(`BLOCK_SIZE) begin
                @(posedge clk) zero_ready = 1'b0;
            end
        end
    endtask

    initial begin
        rand_ready = 1'b0;
        zero_ready = 1'b0; 
        n_drive(10);
        repeat(3)
            zero_drive();
        $finish();
    end
endmodule

src/v/mxint8_negate.v
`ifndef  MXINT8_NEGATE__V
`define  MXINT8_NEGATE__V

module mxint8_negate (
    i_mxint8_elements,
    o_mxint8_elements
);

    `include "mxint8_includes.v"

    input   wire [0:`BLOCK_SIZE-1][`MXINT8_ELEMENT_WIDTH-1:0] i_mxint8_elements;
    output  wire [0:`BLOCK_SIZE-1][`MXINT8_ELEMENT_WIDTH-1:0] o_mxint8_elements;

    genvar i;
    generate
        for (i = 0; i < `BLOCK_SIZE; i = i + 1) begin
            assign o_mxint8_elements[i] = ~i_mxint8_elements[i] + 8'b0000_0001;
        end
    endgenerate

endmodule
`endif

tb/tb_mxint8_negate_v/tb_mxint8_negate.sv
`timescale 1ns/1ps
`define CYCLE 10
module tb_mxint8_negate; 
    `include "mxint8_negate.v"
    bit clk;
    wire [0:`BLOCK_SIZE-1][`MXINT8_ELEMENT_WIDTH-1:0] dut_i_mxint8_elements;
    wire [0:`BLOCK_SIZE-1][`MXINT8_ELEMENT_WIDTH-1:0] dut_o_mxint8_elements;
    wire data_ready;
   
    mxint8_negate uut (
        .i_mxint8_elements(dut_i_mxint8_elements),
        .o_mxint8_elements(dut_o_mxint8_elements)
    );

    mx_int8_negate_drv drv(
        .clk(clk),
        .gen_mxint8_elements(dut_i_mxint8_elements),
        .data_ready_o(data_ready)
    );

    mx_int8_negate_mon mon(
      .clk(clk),
      .dut_in_mxint8_elements(dut_i_mxint8_elements),
      .dut_out_mxint8_elements(dut_o_mxint8_elements),
      .data_ready_i(data_ready)
    );

    initial begin
        clk = 1'b0;
        forever begin
          #(`CYCLE/2)  clk = ~ clk;
        end
    end

    initial begin
        $dumpfile("test.vcd");
        $dumpvars(0,tb_mxint8_negate);
    end
endmodule

tb/tb_mxint8_negate_v/test.vcd
$date
	Thu Oct 10 15:18:37 2024
$end
$version
	Icarus Verilog
$end
$timescale
	1ps
$end
$scope module tb_mxint8_negate $end
$var wire 1 ! data_ready $end
$var reg 1 " clk $end
$scope module drv $end
$var wire 1 " clk $end
$var wire 1 ! data_ready_o $end
$var reg 1 # rand_ready $end
$var reg 1 $ zero_ready $end
$scope module data_in $end
$var reg 8 % scalar [7:0] $end
$var reg 6 & zero_num [5:0] $end
$scope function set_zero $end
$var integer 32 ' elem_index [31:0] $end
$upscope $end
$scope task post_randomize $end
$scope begin $ivl_foreach0 $end
$var integer 32 ( i [31:0] $end
$upscope $end
$upscope $end
$scope task randomize $end
$scope begin $ivl_foreach1 $end
$var integer 32 ) i [31:0] $end
$upscope $end
$upscope $end
$upscope $end
$scope task n_drive $end
$var integer 32 * n [31:0] $end
$upscope $end
$scope task single_drive $end
$upscope $end
$scope task zero_drive $end
$var reg 5 + zero_index [4:0] $end
$upscope $end
$upscope $end
$scope module mon $end
$var wire 1 " clk $end
$var wire 1 ! data_ready_i $end
$var real 1 , decoded_in $end
$var real 1 - decoded_out $end
$var integer 32 . transection_id [31:0] $end
$scope task decoder $end
$scope begin $ivl_for_loop1 $end
$upscope $end
$upscope $end
$scope task single_mon $end
$scope begin $ivl_for_loop0 $end
$var integer 32 / i [31:0] $end
$upscope $end
$upscope $end
$upscope $end
$scope module uut $end
$scope begin genblk1[0] $end
$var parameter 2 0 i $end
$upscope $end
$scope begin genblk1[1] $end
$var parameter 2 1 i $end
$upscope $end
$scope begin genblk1[2] $end
$var parameter 3 2 i $end
$upscope $end
$scope begin genblk1[3] $end
$var parameter 3 3 i $end
$upscope $end
$scope begin genblk1[4] $end
$var parameter 4 4 i $end
$upscope $end
$scope begin genblk1[5] $end
$var parameter 4 5 i $end
$upscope $end
$scope begin genblk1[6] $end
$var parameter 4 6 i $end
$upscope $end
$scope begin genblk1[7] $end
$var parameter 4 7 i $end
$upscope $end
$scope begin genblk1[8] $end
$var parameter 5 8 i $end
$upscope $end
$scope begin genblk1[9] $end
$var parameter 5 9 i $end
$upscope $end
$scope begin genblk1[10] $end
$var parameter 5 : i $end
$upscope $end
$scope begin genblk1[11] $end
$var parameter 5 ; i $end
$upscope $end
$scope begin genblk1[12] $end
$var parameter 5 < i $end
$upscope $end
$scope begin genblk1[13] $end
$var parameter 5 = i $end
$upscope $end
$scope begin genblk1[14] $end
$var parameter 5 > i $end
$upscope $end
$scope begin genblk1[15] $end
$var parameter 5 ? i $end
$upscope $end
$scope begin genblk1[16] $end
$var parameter 6 @ i $end
$upscope $end
$scope begin genblk1[17] $end
$var parameter 6 A i $end
$upscope $end
$scope begin genblk1[18] $end
$var parameter 6 B i $end
$upscope $end
$scope begin genblk1[19] $end
$var parameter 6 C i $end
$upscope $end
$scope begin genblk1[20] $end
$var parameter 6 D i $end
$upscope $end
$scope begin genblk1[21] $end
$var parameter 6 E i $end
$upscope $end
$scope begin genblk1[22] $end
$var parameter 6 F i $end
$upscope $end
$scope begin genblk1[23] $end
$var parameter 6 G i $end
$upscope $end
$scope begin genblk1[24] $end
$var parameter 6 H i $end
$upscope $end
$scope begin genblk1[25] $end
$var parameter 6 I i $end
$upscope $end
$scope begin genblk1[26] $end
$var parameter 6 J i $end
$upscope $end
$scope begin genblk1[27] $end
$var parameter 6 K i $end
$upscope $end
$scope begin genblk1[28] $end
$var parameter 6 L i $end
$upscope $end
$scope begin genblk1[29] $end
$var parameter 6 M i $end
$upscope $end
$scope begin genblk1[30] $end
$var parameter 6 N i $end
$upscope $end
$scope begin genblk1[31] $end
$var parameter 6 O i $end
$upscope $end
$upscope $end
$upscope $end
$enddefinitions $end
$comment Show the parameter values. $end
$dumpall
b11111 O
b11110 N
b11101 M
b11100 L
b11011 K
b11010 J
b11001 I
b11000 H
b10111 G
b10110 F
b10101 E
b10100 D
b10011 C
b10010 B
b10001 A
b10000 @
b1111 ?
b1110 >
b1101 =
b1100 <
b1011 ;
b1010 :
b1001 9
b1000 8
b111 7
b110 6
b101 5
b100 4
b11 3
b10 2
b1 1
b0 0
$end
#0
$dumpvars
b0 /
b0 .
r0 -
r0 ,
bx +
b1010 *
b100000 )
b100000 (
b0 '
b0 &
b100100 %
0$
0#
0"
0!
$end
#5000
b100000 (
b100000 )
b100000 %
1"
#6000
1!
1#
#10000
0"
#15000
b1 /
0!
r1.34375 -
r-1.34375 ,
0#
1"
#20000
0"
#25000
b10 /
r1.546875 -
r-1.546875 ,
1"
#30000
0"
#35000
b11 /
r1.65625 -
r-1.65625 ,
1"
#40000
0"
#45000
b100 /
r-0.296875 -
r0.296875 ,
1"
#50000
0"
#55000
b101 /
r-0.203125 -
r0.203125 ,
1"
#60000
0"
#65000
b110 /
r-1.296875 -
r1.296875 ,
1"
#70000
0"
#75000
b111 /
r-1.671875 -
r1.671875 ,
1"
#80000
0"
#85000
b1000 /
r0.671875 -
r-0.671875 ,
1"
#90000
0"
#95000
b1001 /
r-0.03125 -
r0.03125 ,
1"
#100000
0"
#105000
b1010 /
r1.28125 -
r-1.28125 ,
1"
#110000
0"
#115000
b1011 /
r-0.453125 -
r0.453125 ,
1"
#120000
0"
#125000
b1100 /
r0.765625 -
r-0.765625 ,
1"
#130000
0"
#135000
b1101 /
r-0.546875 -
r0.546875 ,
1"
#140000
0"
#145000
b1110 /
r-0.15625 -
r0.15625 ,
1"
#150000
0"
#155000
b1111 /
r0.84375 -
r-0.84375 ,
1"
#160000
0"
#165000
b10000 /
r-0.9375 -
r0.9375 ,
1"
#170000
0"
#175000
b10001 /
r0.21875 -
r-0.21875 ,
1"
#180000
0"
#185000
b10010 /
r1.84375 -
r-1.84375 ,
1"
#190000
0"
#195000
b10011 /
r-1.015625 -
r1.015625 ,
1"
#200000
0"
#205000
b10100 /
r0.625 -
r-0.625 ,
1"
#210000
0"
#215000
b10101 /
r-1.875 -
r1.875 ,
1"
#220000
0"
#225000
b10110 /
r1.859375 -
r-1.859375 ,
1"
#230000
0"
#235000
b10111 /
r0.328125 -
r-0.328125 ,
1"
#240000
0"
#245000
b11000 /
r1.15625 -
r-1.15625 ,
1"
#250000
0"
#255000
b11001 /
r0.90625 -
r-0.90625 ,
1"
#260000
0"
#265000
b11010 /
r1.28125 -
r-1.28125 ,
1"
#270000
0"
#275000
b11011 /
r1.0625 -
r-1.0625 ,
1"
#280000
0"
#285000
b11100 /
r-0.65625 -
r0.65625 ,
1"
#290000
0"
#295000
b11101 /
r-0.171875 -
r0.171875 ,
1"
#300000
0"
#305000
b11110 /
r-1.765625 -
r1.765625 ,
1"
#310000
0"
#315000
b11111 /
r1.921875 -
r-1.921875 ,
1"
#320000
0"
#325000
b1 .
b100000 /
r-1.234375 -
r1.234375 ,
b100000 (
b100000 )
b111011 %
1"
#330000
0"
#335000
b100000 (
b100000 )
b1111000 %
1"
#336000
b0 /
1!
1#
#340000
0"
#345000
b1 /
0!
r-1.421875 -
r1.421875 ,
0#
1"
#350000
0"
#355000
b10 /
r-1.140625 -
r1.140625 ,
1"
#360000
0"
#365000
b11 /
r-0.984375 -
r0.984375 ,
1"
#370000
0"
#375000
b100 /
r-0.65625 -
r0.65625 ,
1"
#380000
0"
#385000
b101 /
r-1.375 -
r1.375 ,
1"
#390000
0"
#395000
b110 /
r1.90625 -
r-1.90625 ,
1"
#400000
0"
#405000
b111 /
r1.78125 -
r-1.78125 ,
1"
#410000
0"
#415000
b1000 /
r1.5625 -
r-1.5625 ,
1"
#420000
0"
#425000
b1001 /
r0.09375 -
r-0.09375 ,
1"
#430000
0"
#435000
b1010 /
r-0.59375 -
r0.59375 ,
1"
#440000
0"
#445000
b1011 /
r-1.796875 -
r1.796875 ,
1"
#450000
0"
#455000
b1100 /
r1.453125 -
r-1.453125 ,
1"
#460000
0"
#465000
b1101 /
r-0.734375 -
r0.734375 ,
1"
#470000
0"
#475000
b1110 /
r1.203125 -
r-1.203125 ,
1"
#480000
0"
#485000
b1111 /
r-1.484375 -
r1.484375 ,
1"
#490000
0"
#495000
b10000 /
r-1.0625 -
r1.0625 ,
1"
#500000
0"
#505000
b10001 /
r0.140625 -
r-0.140625 ,
1"
#510000
0"
#515000
b10010 /
r0.828125 -
r-0.828125 ,
1"
#520000
0"
#525000
b10011 /
r0.40625 -
r-0.40625 ,
1"
#530000
0"
#535000
b10100 /
r-1.40625 -
r1.40625 ,
1"
#540000
0"
#545000
b10101 /
r-0.640625 -
r0.640625 ,
1"
#550000
0"
#555000
b10110 /
r0.296875 -
r-0.296875 ,
1"
#560000
0"
#565000
b10111 /
r0.59375 -
r-0.59375 ,
1"
#570000
0"
#575000
b11000 /
r-1.578125 -
r1.578125 ,
1"
#580000
0"
#585000
b11001 /
r1.171875 -
r-1.171875 ,
1"
#590000
0"
#595000
b11010 /
r0.515625 -
r-0.515625 ,
1"
#600000
0"
#605000
b11011 /
r-1.890625 -
r1.890625 ,
1"
#610000
0"
#615000
b11100 /
r-1.0625 -
r1.0625 ,
1"
#620000
0"
#625000
b11101 /
r0.75 -
r-0.75 ,
1"
#630000
0"
#635000
b11110 /
r-0.65625 -
r0.65625 ,
1"
#640000
0"
#645000
b11111 /
r1.328125 -
r-1.328125 ,
1"
#650000
0"
#655000
b10 .
b100000 /
r-0.21875 -
r0.21875 ,
b100000 (
b100000 )
b11011100 %
1"
#660000
0"
#665000
b100000 (
b100000 )
b101110 %
1"
#666000
b0 /
1!
1#
#670000
0"
#675000
b1 /
0!
r-0.125 -
r0.125 ,
0#
1"
#680000
0"
#685000
b10 /
r-0.4375 -
r0.4375 ,
1"
#690000
0"
#695000
b11 /
r0.046875 -
r-0.046875 ,
1"
#700000
0"
#705000
b100 /
r-0.640625 -
r0.640625 ,
1"
#710000
0"
#715000
b101 /
r-0.4375 -
r0.4375 ,
1"
#720000
0"
#725000
b110 /
r1.90625 -
r-1.90625 ,
1"
#730000
0"
#735000
b111 /
r0.59375 -
r-0.59375 ,
1"
#740000
0"
#745000
b1000 /
r-0.953125 -
r0.953125 ,
1"
#750000
0"
#755000
b1001 /
r-1.59375 -
r1.59375 ,
1"
#760000
0"
#765000
b1010 /
r-1.75 -
r1.75 ,
1"
#770000
0"
#775000
b1011 /
r-1.796875 -
r1.796875 ,
1"
#780000
0"
#785000
b1100 /
r1.09375 -
r-1.09375 ,
1"
#790000
0"
#795000
b1101 /
r-1.46875 -
r1.46875 ,
1"
#800000
0"
#805000
b1110 /
r0.09375 -
r-0.09375 ,
1"
#810000
0"
#815000
b1111 /
r0.671875 -
r-0.671875 ,
1"
#820000
0"
#825000
b10000 /
r-0.40625 -
r0.40625 ,
1"
#830000
0"
#835000
b10001 /
r1.109375 -
r-1.109375 ,
1"
#840000
0"
#845000
b10010 /
r-0.859375 -
r0.859375 ,
1"
#850000
0"
#855000
b10011 /
r1.65625 -
r-1.65625 ,
1"
#860000
0"
#865000
b10100 /
r1 -
r-1 ,
1"
#870000
0"
#875000
b10101 /
r-0.59375 -
r0.59375 ,
1"
#880000
0"
#885000
b10110 /
r1.15625 -
r-1.15625 ,
1"
#890000
0"
#895000
b10111 /
r-1.953125 -
r1.953125 ,
1"
#900000
0"
#905000
b11000 /
r0.5625 -
r-0.5625 ,
1"
#910000
0"
#915000
b11001 /
r1.90625 -
r-1.90625 ,
1"
#920000
0"
#925000
b11010 /
r-1.875 -
r1.875 ,
1"
#930000
0"
#935000
b11011 /
r-1.96875 -
r1.96875 ,
1"
#940000
0"
#945000
b11100 /
r0.578125 -
r-0.578125 ,
1"
#950000
0"
#955000
b11101 /
r0.765625 -
r-0.765625 ,
1"
#960000
0"
#965000
b11110 /
r-1.890625 -
r1.890625 ,
1"
#970000
0"
#975000
b11111 /
r0.09375 -
r-0.09375 ,
1"
#980000
0"
#985000
b11 .
b100000 /
r-1.515625 -
r1.515625 ,
b100000 (
b100000 )
b10111 %
1"
#990000
0"
#995000
b100000 (
b100000 )
b10111010 %
1"
#996000
b0 /
1!
1#
#1000000
0"
#1005000
b1 /
0!
r0.9375 -
r-0.9375 ,
0#
1"
#1010000
0"
#1015000
b10 /
r1.109375 -
r-1.109375 ,
1"
#1020000
0"
#1025000
b11 /
r1.71875 -
r-1.71875 ,
1"
#1030000
0"
#1035000
b100 /
r1.1875 -
r-1.1875 ,
1"
#1040000
0"
#1045000
b101 /
r-1.984375 -
r1.984375 ,
1"
#1050000
0"
#1055000
b110 /
r1.90625 -
r-1.90625 ,
1"
#1060000
0"
#1065000
b111 /
r0.09375 -
r-0.09375 ,
1"
#1070000
0"
#1075000
b1000 /
r0.21875 -
r-0.21875 ,
1"
#1080000
0"
#1085000
b1001 /
r-0.78125 -
r0.78125 ,
1"
#1090000
0"
#1095000
b1010 /
r1.046875 -
r-1.046875 ,
1"
#1100000
0"
#1105000
b1011 /
r1.9375 -
r-1.9375 ,
1"
#1110000
0"
#1115000
b1100 /
r0.4375 -
r-0.4375 ,
1"
#1120000
0"
#1125000
b1101 /
r0.84375 -
r-0.84375 ,
1"
#1130000
0"
#1135000
b1110 /
r1.359375 -
r-1.359375 ,
1"
#1140000
0"
#1145000
b1111 /
r1.484375 -
r-1.484375 ,
1"
#1150000
0"
#1155000
b10000 /
r1.78125 -
r-1.78125 ,
1"
#1160000
0"
#1165000
b10001 /
r0.078125 -
r-0.078125 ,
1"
#1170000
0"
#1175000
b10010 /
r-0.171875 -
r0.171875 ,
1"
#1180000
0"
#1185000
b10011 /
r0.265625 -
r-0.265625 ,
1"
#1190000
0"
#1195000
b10100 /
r0.859375 -
r-0.859375 ,
1"
#1200000
0"
#1205000
b10101 /
r-0.84375 -
r0.84375 ,
1"
#1210000
0"
#1215000
b10110 /
r-1.828125 -
r1.828125 ,
1"
#1220000
0"
#1225000
b10111 /
r1.765625 -
r-1.765625 ,
1"
#1230000
0"
#1235000
b11000 /
r-1.671875 -
r1.671875 ,
1"
#1240000
0"
#1245000
b11001 /
r1.875 -
r-1.875 ,
1"
#1250000
0"
#1255000
b11010 /
r1.28125 -
r-1.28125 ,
1"
#1260000
0"
#1265000
b11011 /
r1.578125 -
r-1.578125 ,
1"
#1270000
0"
#1275000
b11100 /
r1.71875 -
r-1.71875 ,
1"
#1280000
0"
#1285000
b11101 /
r-0.625 -
r0.625 ,
1"
#1290000
0"
#1295000
b11110 /
r-0.703125 -
r0.703125 ,
1"
#1300000
0"
#1305000
b11111 /
r-1.171875 -
r1.171875 ,
1"
#1310000
0"
#1315000
b100 .
b100000 /
r0.96875 -
r-0.96875 ,
b100000 (
b100000 )
b11110 %
1"
#1320000
0"
#1325000
b100000 (
b100000 )
b10110001 %
1"
#1326000
b0 /
1!
1#
#1330000
0"
#1335000
b1 /
0!
r-1.328125 -
r1.328125 ,
0#
1"
#1340000
0"
#1345000
b10 /
r0.296875 -
r-0.296875 ,
1"
#1350000
0"
#1355000
b11 /
r-0.671875 -
r0.671875 ,
1"
#1360000
0"
#1365000
b100 /
r0.171875 -
r-0.171875 ,
1"
#1370000
0"
#1375000
b101 /
r1.296875 -
r-1.296875 ,
1"
#1380000
0"
#1385000
b110 /
r-0.609375 -
r0.609375 ,
1"
#1390000
0"
#1395000
b111 /
r1.9375 -
r-1.9375 ,
1"
#1400000
0"
#1405000
b1000 /
r1.390625 -
r-1.390625 ,
1"
#1410000
0"
#1415000
b1001 /
r0.390625 -
r-0.390625 ,
1"
#1420000
0"
#1425000
b1010 /
r1.109375 -
r-1.109375 ,
1"
#1430000
0"
#1435000
b1011 /
r-1.140625 -
r1.140625 ,
1"
#1440000
0"
#1445000
b1100 /
r0.578125 -
r-0.578125 ,
1"
#1450000
0"
#1455000
b1101 /
r0.859375 -
r-0.859375 ,
1"
#1460000
0"
#1465000
b1110 /
r-1.265625 -
r1.265625 ,
1"
#1470000
0"
#1475000
b1111 /
r1.484375 -
r-1.484375 ,
1"
#1480000
0"
#1485000
b10000 /
r-0.65625 -
r0.65625 ,
1"
#1490000
0"
#1495000
b10001 /
r0.09375 -
r-0.09375 ,
1"
#1500000
0"
#1505000
b10010 /
r-1.078125 -
r1.078125 ,
1"
#1510000
0"
#1515000
b10011 /
r1.953125 -
r-1.953125 ,
1"
#1520000
0"
#1525000
b10100 /
r-1.9375 -
r1.9375 ,
1"
#1530000
0"
#1535000
b10101 /
r-1.78125 -
r1.78125 ,
1"
#1540000
0"
#1545000
b10110 /
r0.03125 -
r-0.03125 ,
1"
#1550000
0"
#1555000
b10111 /
r-1.625 -
r1.625 ,
1"
#1560000
0"
#1565000
b11000 /
r-1.734375 -
r1.734375 ,
1"
#1570000
0"
#1575000
b11001 /
r1.90625 -
r-1.90625 ,
1"
#1580000
0"
#1585000
b11010 /
r0.25 -
r-0.25 ,
1"
#1590000
0"
#1595000
b11011 /
r-0.875 -
r0.875 ,
1"
#1600000
0"
#1605000
b11100 /
r-1 -
r1 ,
1"
#1610000
0"
#1615000
b11101 /
r-0.625 -
r0.625 ,
1"
#1620000
0"
#1625000
b11110 /
r0.15625 -
r-0.15625 ,
1"
#1630000
0"
#1635000
b11111 /
r0.921875 -
r-0.921875 ,
1"
#1640000
0"
#1645000
b101 .
b100000 /
r1 -
r-1 ,
b100000 (
b100000 )
b1110100 %
1"
#1650000
0"
#1655000
b100000 (
b100000 )
b1111001 %
1"
#1656000
b0 /
1!
1#
#1660000
0"
#1665000
b1 /
0!
r1.53125 -
r-1.53125 ,
0#
1"
#1670000
0"
#1675000
b10 /
r0.046875 -
r-0.046875 ,
1"
#1680000
0"
#1685000
b11 /
r-1.921875 -
r1.921875 ,
1"
#1690000
0"
#1695000
b100 /
r1.765625 -
r-1.765625 ,
1"
#1700000
0"
#1705000
b101 /
r-0.046875 -
r0.046875 ,
1"
#1710000
0"
#1715000
b110 /
r0.453125 -
r-0.453125 ,
1"
#1720000
0"
#1725000
b111 /
r-0.453125 -
r0.453125 ,
1"
#1730000
0"
#1735000
b1000 /
r1.234375 -
r-1.234375 ,
1"
#1740000
0"
#1745000
b1001 /
r-1.0625 -
r1.0625 ,
1"
#1750000
0"
#1755000
b1010 /
r1.671875 -
r-1.671875 ,
1"
#1760000
0"
#1765000
b1011 /
r0.5 -
r-0.5 ,
1"
#1770000
0"
#1775000
b1100 /
r0.296875 -
r-0.296875 ,
1"
#1780000
0"
#1785000
b1101 /
r-1.28125 -
r1.28125 ,
1"
#1790000
0"
#1795000
b1110 /
r0.125 -
r-0.125 ,
1"
#1800000
0"
#1805000
b1111 /
r1.796875 -
r-1.796875 ,
1"
#1810000
0"
#1815000
b10000 /
r-1.28125 -
r1.28125 ,
1"
#1820000
0"
#1825000
b10001 /
r1.9375 -
r-1.9375 ,
1"
#1830000
0"
#1835000
b10010 /
r-1.09375 -
r1.09375 ,
1"
#1840000
0"
#1845000
b10011 /
r1.8125 -
r-1.8125 ,
1"
#1850000
0"
#1855000
b10100 /
r1.75 -
r-1.75 ,
1"
#1860000
0"
#1865000
b10101 /
r-0.359375 -
r0.359375 ,
1"
#1870000
0"
#1875000
b10110 /
r-1.65625 -
r1.65625 ,
1"
#1880000
0"
#1885000
b10111 /
r1.9375 -
r-1.9375 ,
1"
#1890000
0"
#1895000
b11000 /
r1.34375 -
r-1.34375 ,
1"
#1900000
0"
#1905000
b11001 /
r-1.9375 -
r1.9375 ,
1"
#1910000
0"
