src/v/mxint8_includes.v

`ifndef MXINT8_INCLUDES

`define MXINT8_INCLUDES

`include "mx_general_includes.v"

`define MXINT8_ELEMENT_SIGN_BIT 7
`define MXINT8_ELEMENT_VALUE_BITS 6:0

`define MXINT8_ELEMENT_WIDTH 8

`endif // MXINT8_INCLUDES

src/v/scalar_includes.v

`ifndef SCALAR_INCLUDES

`define SCALAR_INCLUDES

`define FLOAT32_WIDTH 32

`define FLOAT32_SIGN_BIT 31

`define FLOAT32_MANTISSA_MSB 22
`define FLOAT32_MANTISSA_LSB 0
`define FLOAT32_MANTISSA_BITS `FLOAT32_MANTISSA_MSB:`FLOAT32_MANTISSA_LSB
`define FLOAT32_MANTISSA_WIDTH 23

`define FLOAT32_EXPONENT_MSB 30
`define FLOAT32_EXPONENT_LSB 23
`define FLOAT32_EXPONENT_BITS `FLOAT32_EXPONENT_MSB:`FLOAT32_EXPONENT_LSB
`define FLOAT32_EXPONENT_WIDTH 8

`define FLOAT32_MANTISSA_MXINT8_MSB `FLOAT32_MANTISSA_MSB
`define FLOAT32_MANTISSA_MXINT8_LSB 17
`define FLOAT32_MANTISSA_MXINT8_BITS `FLOAT32_MANTISSA_MXINT8_MSB:`FLOAT32_MANTISSA_MXINT8_LSB

`endif // SCALAR_INCLUDES

tb/tb_mxint8_negate_v/mx_int8_negate_mon.sv
`timescale 1ns/1ps
module mx_int8_negate_mon(
    dut_in_mxint8_elements,
    dut_out_mxint8_elements,
    data_ready_i,
    clk
);
    `include "scalar_includes.v"
    `include "mxint8_includes.v"
    input wire data_ready_i;  
    input wire clk;
    input wire [0:`BLOCK_SIZE-1][`MXINT8_ELEMENT_WIDTH-1:0] dut_in_mxint8_elements;
    input wire [0:`BLOCK_SIZE-1][`MXINT8_ELEMENT_WIDTH-1:0] dut_out_mxint8_elements;
    reg  [0:`BLOCK_SIZE-1][`MXINT8_ELEMENT_WIDTH-1:0] data_in;
    reg real decoded_in;
    reg  [0:`BLOCK_SIZE-1][`MXINT8_ELEMENT_WIDTH-1:0] data_out;
    reg real decoded_out;
    int transection_id; 

    initial begin
        transection_id = 0; 
    end

    always @(posedge data_ready_i) begin
        $display("\ntransection id: %d",transection_id);
        single_mon();
        transection_id <= transection_id + 1; 
    end

    task single_mon;
        for(int i = 0; i < `BLOCK_SIZE; i = i + 1) begin
            @(posedge clk) begin
                data_in[i] <= dut_in_mxint8_elements[i];
                decoder(dut_in_mxint8_elements[i],decoded_in);
                data_out[i] <= dut_out_mxint8_elements[i];
                decoder(dut_out_mxint8_elements[i],decoded_out);
                #0; 
                $display("element index: %d",i);
                if(decoded_in != (-decoded_out))
                    $display("MXINT8_NEGATE ERROR!");
                $display("input data: %f, output data: %f", decoded_in,decoded_out);
                /*
                $display("input binary: \n%b_%b",data_in[i][`MXINT8_ELEMENT_WIDTH-1],data_in[i][`MXINT8_ELEMENT_WIDTH-2:0]);
                $display("%b\noutput binary",data_out[i][`MXINT8_ELEMENT_WIDTH-1],data_out[i][`MXINT8_ELEMENT_WIDTH-2:0]);
                */
                $display("input binary: \n%b",data_in[i]);
                $display("%b\noutput binary",data_out[i]);
                end
        end
    endtask

    task automatic decoder(input reg[`MXINT8_ELEMENT_WIDTH-1:0] int8_data, output real decimal_data);
        real scale;
        scale = 1.0;
        decimal_data = 0;
        for(int i = `MXINT8_ELEMENT_WIDTH-2 ; i >= 0 ; i = i - 1) begin
            if(int8_data[i]==1'b1)
                decimal_data += scale;
            scale = scale/2;
        end
        if(int8_data[`MXINT8_ELEMENT_WIDTH-1])
            decimal_data -= 2; 
    endtask
endmodule

tb/transection.sv
//`ifndef TRANSECTION__SV
//`define TRANSECTION__SV
`include "scalar_includes.v"
`include "mxint8_includes.v"

`define FLOAT32_MANTISSA_MXINT8_WIDTH `MXINT8_ELEMENT_WIDTH-2
`define FLOAT32_MANTISSA_MXINT8_WIDTH_CUT `FLOAT32_MANTISSA_WIDTH-(`FLOAT32_MANTISSA_MXINT8_WIDTH)
typedef reg[`MXINT8_ELEMENT_WIDTH-1:0] t_mx_int8;
typedef reg[`SCALE_WIDTH-1:0] t_scalar;

module t_mx_int8_vector(
    output t_scalar scalar,
    output t_mx_int8 elements[0:`BLOCK_SIZE-1]);

    reg is_nan;
    reg [$clog2(`BLOCK_SIZE):0] zero_num;

    task post_randomize();
        zero_num = 0; 
        foreach (elements[i]) begin
          if (elements[i] == 0) begin
            zero_num++;
          end
        end
    endtask

    task randomize();
        scalar = $random() % 256;
        foreach(elements[i])
            elements[i] = $random() % 256;
        post_randomize();
    endtask

    function void set_zero(int elem_index);
        if(elements[elem_index] != 0) begin
            elements[elem_index] = 0;
            zero_num++;
        end
    endfunction

endmodule

module op_negate_int8;
    output wire [7:0] input_scalar;
    output wire [7:0] output_scalar;
    output wire [7:0] input_elements[0:31];
    output wire [7:0] output_elements[0:31];

    t_mx_int8_vector a(.scalar(input_scalar),.elements(input_elements));
    t_mx_int8_vector result(.scalar(output_scalar),.elements(output_elements));

endmodule

module t_fp32_scalar(output [`FLOAT32_WIDTH-1:0] f);
    reg sign;
    reg sub_normal;
    reg NaN; 
    reg [`FLOAT32_EXPONENT_WIDTH-1:0] scalar;
    reg carry; 
    reg[1:0] tie2even; //lsb: whether valid, MSB whether carry  
    reg overflow; //mantissa overflow, scalar carry
    reg scalar_overflow;
    reg [`FLOAT32_MANTISSA_MXINT8_WIDTH-1:0] mantissa_high; 
    reg [`FLOAT32_MANTISSA_MXINT8_WIDTH_CUT-2:0] mantissa_low;
    reg mantissa_low_msb;  
    assign f = {sign,scalar,mantissa_high,mantissa_low_msb,mantissa_low};
    initial begin
        set_clean();
        randomize();
    end
    function void set_zero();
        {mantissa_high,mantissa_low_msb,mantissa_low} = `FLOAT32_MANTISSA_WIDTH'd0;
    endfunction
    function void set_clean();
        sign = 1'b0;
        sub_normal = 1'b0;
        NaN = 1'b0;
        carry = 1'b0;
        tie2even = 2'b00;
        overflow = 1'b0;
        scalar_overflow = 1'b0; 
    endfunction
    function [`FLOAT32_MANTISSA_MXINT8_WIDTH-1:0] random_high();
        return $urandom()%(1<<`FLOAT32_MANTISSA_MXINT8_WIDTH);
    endfunction
    function [`FLOAT32_MANTISSA_MXINT8_WIDTH_CUT-2:0] random_low();
        return $urandom()%(1<<(`FLOAT32_MANTISSA_MXINT8_WIDTH_CUT-1));
    endfunction
    function random_bit();
        return $urandom() % 2; 
    endfunction
    function void set_sign(input sign_i);
        sign = sign_i;
    endfunction
    function void set_carry(input c_i);//round causes carry, should't set tie2even = 01
        carry = c_i;
    endfunction
    function void set_overflow(input o_i);//carry causes mantissa overflow 
        overflow = o_i;
        carry = 1'b1; 
    endfunction
    function void set_NaN(input NaN_i);
        NaN = NaN_i; 
    endfunction
    function void set_tie2even();//0.5 whether carry or not// valid when carry == 1
        tie2even = {random_bit(),1'b1};
        carry = 1'b1;   
    endfunction
    function void set_scalar_overflow(input overflow_i);
        scalar_overflow = overflow_i;
        if(scalar_overflow) begin
            carry = 1'b1;
            overflow = 1'b1;
            NaN = 1'b0; 
        end
    endfunction
    function void randomize();
        if(sub_normal)
            scalar = `FLOAT32_EXPONENT_WIDTH'b0;
        else if(NaN)
            scalar = {`FLOAT32_EXPONENT_WIDTH{1'b1}};
        else
            scalar = $urandom() % (2<<`FLOAT32_EXPONENT_WIDTH-2) +1'b1;
        if(scalar_overflow)
            scalar = {`FLOAT32_EXPONENT_WIDTH{1'b1}}-1'b1;
        mantissa_high = random_high();
        mantissa_low = random_low();
        mantissa_low_msb = random_bit();
        if(carry) begin
            mantissa_low_msb = 1'b1;
            while(&mantissa_low)
                mantissa_low = random_low();
            if(tie2even[0]) begin
                mantissa_low_msb = 1'b1;
                mantissa_low = 0;
                mantissa_high[0] = tie2even[1]; 
            end
        end
        if(overflow)
            mantissa_high = (1<<`FLOAT32_MANTISSA_MXINT8_WIDTH) - 1; 
    endfunction
endmodule
//`endif

tb/tb_mxint8_negate_v/mx_int8_negate_drv.sv
`timescale 1ns/1ps
module mx_int8_negate_drv(
    gen_mxint8_elements,
    data_ready_o,
    clk
);
    `include "scalar_includes.v"
    `include "mxint8_includes.v"
    input wire clk;
    output wire [0:`BLOCK_SIZE-1][`MXINT8_ELEMENT_WIDTH-1:0] gen_mxint8_elements ;
    output wire data_ready_o; 
    t_mx_int8_vector data_in(.elements(gen_mxint8_elements));
    reg rand_ready;
    reg zero_ready;
    assign data_ready_o = rand_ready || zero_ready; 
    task single_drive();
        data_in.randomize(); 
        @(posedge clk) begin
            data_in.randomize();
            #1;
            rand_ready = 1'b1;
            repeat(`BLOCK_SIZE) begin
                @(posedge clk) rand_ready = 1'b0;
            end
        end
    endtask

    task n_drive(int n);   
        repeat(n)
            single_drive();
    endtask

    task zero_drive();     
        logic [$clog2(`BLOCK_SIZE)-1:0] zero_index;  
        @(posedge clk) begin
            zero_index = $urandom() % `BLOCK_SIZE;
            data_in.randomize();
            data_in.set_zero(zero_index);
            #1;
            $display("zero element index: %d", zero_index);
            zero_ready = 1'b1; 
            repeat(`BLOCK_SIZE) begin
                @(posedge clk) zero_ready = 1'b0;
            end
        end
    endtask

    initial begin
        rand_ready = 1'b0;
        zero_ready = 1'b0; 
        n_drive(10);
        repeat(3)
            zero_drive();
        $finish();
    end
endmodule

src/v/mxint8_negate.v
`ifndef  MXINT8_NEGATE__V
`define  MXINT8_NEGATE__V

module mxint8_negate (
    i_mxint8_elements,
    o_mxint8_elements
);

    `include "mxint8_includes.v"

    input   wire [0:`BLOCK_SIZE-1][`MXINT8_ELEMENT_WIDTH-1:0] i_mxint8_elements;
    output  wire [0:`BLOCK_SIZE-1][`MXINT8_ELEMENT_WIDTH-1:0] o_mxint8_elements;

    genvar i;
    generate
        for (i = 0; i < `BLOCK_SIZE; i = i + 1) begin
            assign o_mxint8_elements[i] = ~i_mxint8_elements[i] + 8'b0000_0001;
        end
    endgenerate

endmodule
`endif

tb/tb_mxint8_negate_v/tb_mxint8_negate.sv
`timescale 1ns/1ps
`define CYCLE 10
module tb_mxint8_negate; 
    `include "mxint8_negate.v"
    bit clk;
    wire [0:`BLOCK_SIZE-1][`MXINT8_ELEMENT_WIDTH-1:0] dut_i_mxint8_elements;
    wire [0:`BLOCK_SIZE-1][`MXINT8_ELEMENT_WIDTH-1:0] dut_o_mxint8_elements;
    wire data_ready;
   
    mxint8_negate uut (
        .i_mxint8_elements(dut_i_mxint8_elements),
        .o_mxint8_elements(dut_o_mxint8_elements)
    );

    mx_int8_negate_drv drv(
        .clk(clk),
        .gen_mxint8_elements(dut_i_mxint8_elements),
        .data_ready_o(data_ready)
    );

    mx_int8_negate_mon mon(
      .clk(clk),
      .dut_in_mxint8_elements(dut_i_mxint8_elements),
      .dut_out_mxint8_elements(dut_o_mxint8_elements),
      .data_ready_i(data_ready)
    );

    initial begin
        clk = 1'b0;
        forever begin
          #(`CYCLE/2)  clk = ~ clk;
        end
    end

    initial begin
        $dumpfile("test.vcd");
        $dumpvars(0,tb_mxint8_negate);
    end
endmodule

tb/tb_mxint8_negate_v/test.vcd
$date
	Tue Aug 27 10:13:10 2024
$end
$version
	Icarus Verilog
$end
$timescale
	1ps
$end
$scope module tb_mxint8_negate $end
$var wire 256 ! dut_o_mxint8_elements [255:0] $end
$var wire 256 " dut_i_mxint8_elements [255:0] $end
$var wire 1 # data_ready $end
$var reg 1 $ clk $end
$scope module drv $end
$var wire 1 $ clk $end
$var wire 1 # data_ready_o $end
$var wire 256 % gen_mxint8_elements [255:0] $end
$var reg 1 & rand_ready $end
$var reg 1 ' zero_ready $end
$scope module data_in $end
$var reg 256 ( elements [255:0] $end
$var reg 8 ) scalar [7:0] $end
$var reg 6 * zero_num [5:0] $end
$scope function set_zero $end
$var integer 32 + elem_index [31:0] $end
$upscope $end
$scope task post_randomize $end
$scope begin $ivl_foreach0 $end
$var integer 32 , i [31:0] $end
$upscope $end
$upscope $end
$scope task randomize $end
$scope begin $ivl_foreach1 $end
$var integer 32 - i [31:0] $end
$upscope $end
$upscope $end
$upscope $end
$scope task n_drive $end
$var integer 32 . n [31:0] $end
$upscope $end
$scope task single_drive $end
$upscope $end
$scope task zero_drive $end
$var reg 5 / zero_index [4:0] $end
$upscope $end
$upscope $end
$scope module mon $end
$var wire 1 $ clk $end
$var wire 1 # data_ready_i $end
$var wire 256 0 dut_in_mxint8_elements [255:0] $end
$var wire 256 1 dut_out_mxint8_elements [255:0] $end
$var reg 256 2 data_in [255:0] $end
$var reg 256 3 data_out [255:0] $end
$var real 1 4 decoded_in $end
$var real 1 5 decoded_out $end
$var integer 32 6 transection_id [31:0] $end
$scope task decoder $end
$scope begin $ivl_for_loop1 $end
$upscope $end
$upscope $end
$scope task single_mon $end
$scope begin $ivl_for_loop0 $end
$var integer 32 7 i [31:0] $end
$upscope $end
$upscope $end
$upscope $end
$scope module uut $end
$var wire 256 8 i_mxint8_elements [255:0] $end
$var wire 256 9 o_mxint8_elements [255:0] $end
$scope begin genblk1[0] $end
$var parameter 2 : i $end
$upscope $end
$scope begin genblk1[1] $end
$var parameter 2 ; i $end
$upscope $end
$scope begin genblk1[2] $end
$var parameter 3 < i $end
$upscope $end
$scope begin genblk1[3] $end
$var parameter 3 = i $end
$upscope $end
$scope begin genblk1[4] $end
$var parameter 4 > i $end
$upscope $end
$scope begin genblk1[5] $end
$var parameter 4 ? i $end
$upscope $end
$scope begin genblk1[6] $end
$var parameter 4 @ i $end
$upscope $end
$scope begin genblk1[7] $end
$var parameter 4 A i $end
$upscope $end
$scope begin genblk1[8] $end
$var parameter 5 B i $end
$upscope $end
$scope begin genblk1[9] $end
$var parameter 5 C i $end
$upscope $end
$scope begin genblk1[10] $end
$var parameter 5 D i $end
$upscope $end
$scope begin genblk1[11] $end
$var parameter 5 E i $end
$upscope $end
$scope begin genblk1[12] $end
$var parameter 5 F i $end
$upscope $end
$scope begin genblk1[13] $end
$var parameter 5 G i $end
$upscope $end
$scope begin genblk1[14] $end
$var parameter 5 H i $end
$upscope $end
$scope begin genblk1[15] $end
$var parameter 5 I i $end
$upscope $end
$scope begin genblk1[16] $end
$var parameter 6 J i $end
$upscope $end
$scope begin genblk1[17] $end
$var parameter 6 K i $end
$upscope $end
$scope begin genblk1[18] $end
$var parameter 6 L i $end
$upscope $end
$scope begin genblk1[19] $end
$var parameter 6 M i $end
$upscope $end
$scope begin genblk1[20] $end
$var parameter 6 N i $end
$upscope $end
$scope begin genblk1[21] $end
$var parameter 6 O i $end
$upscope $end
$scope begin genblk1[22] $end
$var parameter 6 P i $end
$upscope $end
$scope begin genblk1[23] $end
$var parameter 6 Q i $end
$upscope $end
$scope begin genblk1[24] $end
$var parameter 6 R i $end
$upscope $end
$scope begin genblk1[25] $end
$var parameter 6 S i $end
$upscope $end
$scope begin genblk1[26] $end
$var parameter 6 T i $end
$upscope $end
$scope begin genblk1[27] $end
$var parameter 6 U i $end
$upscope $end
$scope begin genblk1[28] $end
$var parameter 6 V i $end
$upscope $end
$scope begin genblk1[29] $end
$var parameter 6 W i $end
$upscope $end
$scope begin genblk1[30] $end
$var parameter 6 X i $end
$upscope $end
$scope begin genblk1[31] $end
$var parameter 6 Y i $end
$upscope $end
$upscope $end
$upscope $end
$enddefinitions $end
$comment Show the parameter values. $end
$dumpall
b11111 Y
b11110 X
b11101 W
b11100 V
b11011 U
b11010 T
b11001 S
b11000 R
b10111 Q
b10110 P
b10101 O
b10100 N
b10011 M
b10010 L
b10001 K
b10000 J
b1111 I
b1110 H
b1101 G
b1100 F
b1011 E
b1010 D
b1001 C
b1000 B
b111 A
b110 @
b101 ?
b100 >
b11 =
b10 <
b1 ;
b0 :
$end
#0
$dumpvars
b111111111110111100111011111001101110011100110111110111011111111111100111000101011000011000100110111010000000111001110100011101101010110000110111000100111101110011100010000111000110010000110000011101110100100010000111101001110011011100111011111011010000000 9
b1000000100001001011000110000110110001101011001010001001000000001000011010111011000111101111011011000110011111001110001101100010110101010111001010111011100010010100011111111001011001110111010001100010101011100101111010010110101100101011000110000101010000000 8
b0 7
b0 6
r0 5
r0 4
bx 3
bx 2
b111111111110111100111011111001101110011100110111110111011111111111100111000101011000011000100110111010000000111001110100011101101010110000110111000100111101110011100010000111000110010000110000011101110100100010000111101001110011011100111011111011010000000 1
b1000000100001001011000110000110110001101011001010001001000000001000011010111011000111101111011011000110011111001110001101100010110101010111001010111011100010010100011111111001011001110111010001100010101011100101111010010110101100101011000110000101010000000 0
bx /
b1010 .
b100000 -
b100000 ,
b0 +
b0 *
b100100 )
b1000000100001001011000110000110110001101011001010001001000000001000011010111011000111101111011011000110011111001110001101100010110101010111001010111011100010010100011111111001011001110111010001100010101011100101111010010110101100101011000110000101010000000 (
0'
0&
b1000000100001001011000110000110110001101011001010001001000000001000011010111011000111101111011011000110011111001110001101100010110101010111001010111011100010010100011111111001011001110111010001100010101011100101111010010110101100101011000110000101010000000 %
0$
0#
b1000000100001001011000110000110110001101011001010001001000000001000011010111011000111101111011011000110011111001110001101100010110101010111001010111011100010010100011111111001011001110111010001100010101011100101111010010110101100101011000110000101010000000 "
b111111111110111100111011111001101110011100110111110111011111111111100111000101011000011000100110111010000000111001110100011101101010110000110111000100111101110011100010000111000110010000110000011101110100100010000111101001110011011100111011111011010000000 !
$end
#5000
b101011001100011011010101110110111110011101011011001010100101011111111100101001011100011001100011101110111110110001101101100010000001110011101101011111100101000100010000111011100010101010010100011101001010010010001001101011011110101100011110111101110110001 !
b101011001100011011010101110110111110011101011011001010100101011111111100101001011100011001100011101110111110110001101101100010000001110011101101011111100101000100010000111011100010101010010100011101001010010010001001101011011110101100011110111101110110001 1
b101011001100011011010101110110111110011101011011001010100101011111111100101001011100011001100011101110111110110001101101100010000001110011101101011111100101000100010000111011100010101010010100011101001010010010001001101011011110101100011110111101110110001 9
b100000 ,
b1010101010011101100101100001001100001101010100110110101111010101000000101010111000011101110011110010001100001010110010100011110011110010100010100100000111011000011110001000100111101011101101101100011010101110101111000010101000001011011100011000010101001111 "
b1010101010011101100101100001001100001101010100110110101111010101000000101010111000011101110011110010001100001010110010100011110011110010100010100100000111011000011110001000100111101011101101101100011010101110101111000010101000001011011100011000010101001111 %
b1010101010011101100101100001001100001101010100110110101111010101000000101010111000011101110011110010001100001010110010100011110011110010100010100100000111011000011110001000100111101011101101101100011010101110101111000010101000001011011100011000010101001111 (
b1010101010011101100101100001001100001101010100110110101111010101000000101010111000011101110011110010001100001010110010100011110011110010100010100100000111011000011110001000100111101011101101101100011010101110101111000010101000001011011100011000010101001111 0
b1010101010011101100101100001001100001101010100110110101111010101000000101010111000011101110011110010001100001010110010100011110011110010100010100100000111011000011110001000100111101011101101101100011010101110101111000010101000001011011100011000010101001111 8
b100000 -
b100000 )
1$
#6000
1#
1&
#10000
0$
#15000
b1010110xxxxxxxxxxxxxxxxxxxxxxxxxxxxxxxxxxxxxxxxxxxxxxxxxxxxxxxxxxxxxxxxxxxxxxxxxxxxxxxxxxxxxxxxxxxxxxxxxxxxxxxxxxxxxxxxxxxxxxxxxxxxxxxxxxxxxxxxxxxxxxxxxxxxxxxxxxxxxxxxxxxxxxxxxxxxxxxxxxxxxxxxxxxxxxxxxxxxxxxxxxxxxxxxxxxxxxxxxxxxxxxxxxxxxxxxxxxxxxxxxxxxxxxx 3
b10101010xxxxxxxxxxxxxxxxxxxxxxxxxxxxxxxxxxxxxxxxxxxxxxxxxxxxxxxxxxxxxxxxxxxxxxxxxxxxxxxxxxxxxxxxxxxxxxxxxxxxxxxxxxxxxxxxxxxxxxxxxxxxxxxxxxxxxxxxxxxxxxxxxxxxxxxxxxxxxxxxxxxxxxxxxxxxxxxxxxxxxxxxxxxxxxxxxxxxxxxxxxxxxxxxxxxxxxxxxxxxxxxxxxxxxxxxxxxxxxxxxxxxxxxx 2
b1 7
0#
r1.34375 5
r-1.34375 4
0&
1$
#20000
0$
#25000
b101011001100011xxxxxxxxxxxxxxxxxxxxxxxxxxxxxxxxxxxxxxxxxxxxxxxxxxxxxxxxxxxxxxxxxxxxxxxxxxxxxxxxxxxxxxxxxxxxxxxxxxxxxxxxxxxxxxxxxxxxxxxxxxxxxxxxxxxxxxxxxxxxxxxxxxxxxxxxxxxxxxxxxxxxxxxxxxxxxxxxxxxxxxxxxxxxxxxxxxxxxxxxxxxxxxxxxxxxxxxxxxxxxxxxxxxxxxxxxxxxxxxx 3
b1010101010011101xxxxxxxxxxxxxxxxxxxxxxxxxxxxxxxxxxxxxxxxxxxxxxxxxxxxxxxxxxxxxxxxxxxxxxxxxxxxxxxxxxxxxxxxxxxxxxxxxxxxxxxxxxxxxxxxxxxxxxxxxxxxxxxxxxxxxxxxxxxxxxxxxxxxxxxxxxxxxxxxxxxxxxxxxxxxxxxxxxxxxxxxxxxxxxxxxxxxxxxxxxxxxxxxxxxxxxxxxxxxxxxxxxxxxxxxxxxxxxxx 2
b10 7
r1.546875 5
r-1.546875 4
1$
#30000
0$
#35000
b10101100110001101101010xxxxxxxxxxxxxxxxxxxxxxxxxxxxxxxxxxxxxxxxxxxxxxxxxxxxxxxxxxxxxxxxxxxxxxxxxxxxxxxxxxxxxxxxxxxxxxxxxxxxxxxxxxxxxxxxxxxxxxxxxxxxxxxxxxxxxxxxxxxxxxxxxxxxxxxxxxxxxxxxxxxxxxxxxxxxxxxxxxxxxxxxxxxxxxxxxxxxxxxxxxxxxxxxxxxxxxxxxxxxxxxxxxxxxxxx 3
b101010101001110110010110xxxxxxxxxxxxxxxxxxxxxxxxxxxxxxxxxxxxxxxxxxxxxxxxxxxxxxxxxxxxxxxxxxxxxxxxxxxxxxxxxxxxxxxxxxxxxxxxxxxxxxxxxxxxxxxxxxxxxxxxxxxxxxxxxxxxxxxxxxxxxxxxxxxxxxxxxxxxxxxxxxxxxxxxxxxxxxxxxxxxxxxxxxxxxxxxxxxxxxxxxxxxxxxxxxxxxxxxxxxxxxxxxxxxxxxx 2
b11 7
r1.65625 5
r-1.65625 4
1$
#40000
0$
#45000
b1010110011000110110101011101101xxxxxxxxxxxxxxxxxxxxxxxxxxxxxxxxxxxxxxxxxxxxxxxxxxxxxxxxxxxxxxxxxxxxxxxxxxxxxxxxxxxxxxxxxxxxxxxxxxxxxxxxxxxxxxxxxxxxxxxxxxxxxxxxxxxxxxxxxxxxxxxxxxxxxxxxxxxxxxxxxxxxxxxxxxxxxxxxxxxxxxxxxxxxxxxxxxxxxxxxxxxxxxxxxxxxxxxxxxxxxxxx 3
b10101010100111011001011000010011xxxxxxxxxxxxxxxxxxxxxxxxxxxxxxxxxxxxxxxxxxxxxxxxxxxxxxxxxxxxxxxxxxxxxxxxxxxxxxxxxxxxxxxxxxxxxxxxxxxxxxxxxxxxxxxxxxxxxxxxxxxxxxxxxxxxxxxxxxxxxxxxxxxxxxxxxxxxxxxxxxxxxxxxxxxxxxxxxxxxxxxxxxxxxxxxxxxxxxxxxxxxxxxxxxxxxxxxxxxxxxxx 2
b100 7
r-0.296875 5
r0.296875 4
1$
#50000
0$
#55000
b101011001100011011010101110110111110011xxxxxxxxxxxxxxxxxxxxxxxxxxxxxxxxxxxxxxxxxxxxxxxxxxxxxxxxxxxxxxxxxxxxxxxxxxxxxxxxxxxxxxxxxxxxxxxxxxxxxxxxxxxxxxxxxxxxxxxxxxxxxxxxxxxxxxxxxxxxxxxxxxxxxxxxxxxxxxxxxxxxxxxxxxxxxxxxxxxxxxxxxxxxxxxxxxxxxxxxxxxxxxxxxxxxxxxx 3
b1010101010011101100101100001001100001101xxxxxxxxxxxxxxxxxxxxxxxxxxxxxxxxxxxxxxxxxxxxxxxxxxxxxxxxxxxxxxxxxxxxxxxxxxxxxxxxxxxxxxxxxxxxxxxxxxxxxxxxxxxxxxxxxxxxxxxxxxxxxxxxxxxxxxxxxxxxxxxxxxxxxxxxxxxxxxxxxxxxxxxxxxxxxxxxxxxxxxxxxxxxxxxxxxxxxxxxxxxxxxxxxxxxxxxx 2
b101 7
r-0.203125 5
r0.203125 4
1$
#60000
0$
#65000
b10101100110001101101010111011011111001110101101xxxxxxxxxxxxxxxxxxxxxxxxxxxxxxxxxxxxxxxxxxxxxxxxxxxxxxxxxxxxxxxxxxxxxxxxxxxxxxxxxxxxxxxxxxxxxxxxxxxxxxxxxxxxxxxxxxxxxxxxxxxxxxxxxxxxxxxxxxxxxxxxxxxxxxxxxxxxxxxxxxxxxxxxxxxxxxxxxxxxxxxxxxxxxxxxxxxxxxxxxxxxxxxx 3
b101010101001110110010110000100110000110101010011xxxxxxxxxxxxxxxxxxxxxxxxxxxxxxxxxxxxxxxxxxxxxxxxxxxxxxxxxxxxxxxxxxxxxxxxxxxxxxxxxxxxxxxxxxxxxxxxxxxxxxxxxxxxxxxxxxxxxxxxxxxxxxxxxxxxxxxxxxxxxxxxxxxxxxxxxxxxxxxxxxxxxxxxxxxxxxxxxxxxxxxxxxxxxxxxxxxxxxxxxxxxxxxx 2
b110 7
r-1.296875 5
r1.296875 4
1$
#70000
0$
#75000
b1010110011000110110101011101101111100111010110110010101xxxxxxxxxxxxxxxxxxxxxxxxxxxxxxxxxxxxxxxxxxxxxxxxxxxxxxxxxxxxxxxxxxxxxxxxxxxxxxxxxxxxxxxxxxxxxxxxxxxxxxxxxxxxxxxxxxxxxxxxxxxxxxxxxxxxxxxxxxxxxxxxxxxxxxxxxxxxxxxxxxxxxxxxxxxxxxxxxxxxxxxxxxxxxxxxxxxxxxxx 3
b10101010100111011001011000010011000011010101001101101011xxxxxxxxxxxxxxxxxxxxxxxxxxxxxxxxxxxxxxxxxxxxxxxxxxxxxxxxxxxxxxxxxxxxxxxxxxxxxxxxxxxxxxxxxxxxxxxxxxxxxxxxxxxxxxxxxxxxxxxxxxxxxxxxxxxxxxxxxxxxxxxxxxxxxxxxxxxxxxxxxxxxxxxxxxxxxxxxxxxxxxxxxxxxxxxxxxxxxxxx 2
b111 7
r-1.671875 5
r1.671875 4
1$
#80000
0$
#85000
b101011001100011011010101110110111110011101011011001010100101011xxxxxxxxxxxxxxxxxxxxxxxxxxxxxxxxxxxxxxxxxxxxxxxxxxxxxxxxxxxxxxxxxxxxxxxxxxxxxxxxxxxxxxxxxxxxxxxxxxxxxxxxxxxxxxxxxxxxxxxxxxxxxxxxxxxxxxxxxxxxxxxxxxxxxxxxxxxxxxxxxxxxxxxxxxxxxxxxxxxxxxxxxxxxxxxx 3
b1010101010011101100101100001001100001101010100110110101111010101xxxxxxxxxxxxxxxxxxxxxxxxxxxxxxxxxxxxxxxxxxxxxxxxxxxxxxxxxxxxxxxxxxxxxxxxxxxxxxxxxxxxxxxxxxxxxxxxxxxxxxxxxxxxxxxxxxxxxxxxxxxxxxxxxxxxxxxxxxxxxxxxxxxxxxxxxxxxxxxxxxxxxxxxxxxxxxxxxxxxxxxxxxxxxxxx 2
b1000 7
r0.671875 5
r-0.671875 4
1$
#90000
0$
#95000
b10101100110001101101010111011011111001110101101100101010010101111111110xxxxxxxxxxxxxxxxxxxxxxxxxxxxxxxxxxxxxxxxxxxxxxxxxxxxxxxxxxxxxxxxxxxxxxxxxxxxxxxxxxxxxxxxxxxxxxxxxxxxxxxxxxxxxxxxxxxxxxxxxxxxxxxxxxxxxxxxxxxxxxxxxxxxxxxxxxxxxxxxxxxxxxxxxxxxxxxxxxxxxxxx 3
b101010101001110110010110000100110000110101010011011010111101010100000010xxxxxxxxxxxxxxxxxxxxxxxxxxxxxxxxxxxxxxxxxxxxxxxxxxxxxxxxxxxxxxxxxxxxxxxxxxxxxxxxxxxxxxxxxxxxxxxxxxxxxxxxxxxxxxxxxxxxxxxxxxxxxxxxxxxxxxxxxxxxxxxxxxxxxxxxxxxxxxxxxxxxxxxxxxxxxxxxxxxxxxxx 2
b1001 7
r-0.03125 5
r0.03125 4
1$
#100000
0$
#105000
b1010110011000110110101011101101111100111010110110010101001010111111111001010010xxxxxxxxxxxxxxxxxxxxxxxxxxxxxxxxxxxxxxxxxxxxxxxxxxxxxxxxxxxxxxxxxxxxxxxxxxxxxxxxxxxxxxxxxxxxxxxxxxxxxxxxxxxxxxxxxxxxxxxxxxxxxxxxxxxxxxxxxxxxxxxxxxxxxxxxxxxxxxxxxxxxxxxxxxxxxxxx 3
b10101010100111011001011000010011000011010101001101101011110101010000001010101110xxxxxxxxxxxxxxxxxxxxxxxxxxxxxxxxxxxxxxxxxxxxxxxxxxxxxxxxxxxxxxxxxxxxxxxxxxxxxxxxxxxxxxxxxxxxxxxxxxxxxxxxxxxxxxxxxxxxxxxxxxxxxxxxxxxxxxxxxxxxxxxxxxxxxxxxxxxxxxxxxxxxxxxxxxxxxxxx 2
b1010 7
r1.28125 5
r-1.28125 4
1$
#110000
0$
#115000
b101011001100011011010101110110111110011101011011001010100101011111111100101001011100011xxxxxxxxxxxxxxxxxxxxxxxxxxxxxxxxxxxxxxxxxxxxxxxxxxxxxxxxxxxxxxxxxxxxxxxxxxxxxxxxxxxxxxxxxxxxxxxxxxxxxxxxxxxxxxxxxxxxxxxxxxxxxxxxxxxxxxxxxxxxxxxxxxxxxxxxxxxxxxxxxxxxxxxx 3
b1010101010011101100101100001001100001101010100110110101111010101000000101010111000011101xxxxxxxxxxxxxxxxxxxxxxxxxxxxxxxxxxxxxxxxxxxxxxxxxxxxxxxxxxxxxxxxxxxxxxxxxxxxxxxxxxxxxxxxxxxxxxxxxxxxxxxxxxxxxxxxxxxxxxxxxxxxxxxxxxxxxxxxxxxxxxxxxxxxxxxxxxxxxxxxxxxxxxxx 2
b1011 7
r-0.453125 5
r0.453125 4
1$
#120000
0$
